Workbook

Sheet 0. Legenda
A1: Plano HIIP - legenda e convenções
A3: Níveis
A4: Projeto | B4: O programa maior. Nesta planilha, apenas o HIIP.
A5: Frente de trabalho (produto) | B5: A frente que produz um produto. É o nível onde vive a validação externa. Cada frente tem a sua aba própria.
A6: Resultado (output) | B6: Entrega intermédia que fecha dentro de uma ou duas sprints. É o nível onde vive a definição de feito.
A7: Tarefa | B7: O trabalho concreto. Não tem critério próprio: está feita ou não está.
A9: Definição de feito e validação
A10: Definição de feito | B10: Critérios internos do resultado, sob o teu controlo. O resultado fecha quando são cumpridos.
A11: Validação externa | B11: Aceitação pelo cliente (TWG-PHC, TWG-PFM, Ministra, financiadores). Existe só ao nível da frente, tem data própria e não está sob o teu controlo.
A12: Tarefas sem resultado | B12: Linhas com o campo Resultado vazio: tarefas que servem diretamente a validação externa da frente.
A14: Definição de feito geral - aplica-se a todos os resultados
A15: 1 | B15: Revisto por ti numa segunda passagem, em dia diferente do da redação.
A16: 2 | B16: Toda afirmação sobre um documento tem referência de página verificável.
A17: 3 | B17: Fontes de dados identificadas, com data de extração.
A18: 4 | B18: Estruturado pelas alavancas do operational framework de CSP da OMS, quando aplicável.
A19: 5 | B19: Versão datada, guardada na biblioteca do SharePoint, com o link registado.
A20: 6 | B20: Revisão do country office sempre que o resultado sai do escritório.
A21: 7 | B21: Português como versão base; inglês quando se destina a parceiros.
A23: Estados
A24: Tarefa | B24: Backlog (identificada) - To do (comprometida para a sprint) - In progress - Blocked (parada por terceiros) - Done.
A25: Resultado | B25: Não iniciado - Em curso - Feito.
A26: Validação | B26: Não iniciada - Em curso - Feita.
A28: Outras colunas
A29: Sprint | B29: Quinzena prevista. Datas na aba Sprints. 'Recorrente' repete-se em todas; 'TBC' aguarda data.
A30: Estimativa | B30: Dias de trabalho. Primeira aproximação, para ser corrigida com o uso.
A31: Depende de | B31: O que tem de estar concluído antes. Se não estiver, a tarefa fica Blocked, não atrasada.
A32: Aprendizado | B32: Informação crítica surgida ao realizar a tarefa: consequências, dados novos, problemas reconhecidos. Preenche-se ao fazer e revê-se na retrospetiva de fecho de sprint.
A34: Abas
A35: 1. Frentes | B35: Uma linha por frente, com validação externa e contagem automática de progresso.
A36: 2. Master | B36: Todas as linhas do plano: frente, resultado, tarefa. É a fonte de verdade.
A37: 3. Tarefas | B37: Backlog plano, ordenado por sprint. Para o planeamento de cada quinzena.
A38: 4. Sprints | B38: Calendário quinzenal de 3 de agosto de 2026 a 2 de julho de 2027.
A39: 5 e seguintes | B39: Uma aba por frente, com o mesmo conteúdo filtrado.
A41: Regra de promoção
B42: Aprendizado que muda o plano não fica só na coluna: vira alteração da definição de feito, tarefa nova ou linha no registo de riscos.

Sheet 1. Frentes
A1: Frentes do HIIP
A3: Frente de trabalho (produto) | B3: Validação externa | C3: Data validação | D3: Estado validação | E3: Resultados | F3: Tarefas | G3: Tarefas feitas | H3: % feito | I3: Aba
A4: TWG-PHC | B4: Autoridades autorizam formalmente a reconstituição do grupo; sessão de refundação realizada com quórum; plano de atividades aceite pelos membros | C4: 46318 | D4: Não iniciada | E4: 1 | F4: 8 | G4: =COUNTIFS('2. Master'!$B$4:$B$162,$A4,'2. Master'!$O$4:$O$162,"Done") -> 0 | H4: =IFERROR($G4/$F4,0) -> 0 | I4: 1. TWG-PHC
A5: Background document - PHC | B5: Apresentado ao TWG-PHC; posição registada sobre o diagnóstico; ata com comentários e responsáveis; alterações incorporadas em versão datada | C5: 46332 | D5: Não iniciada | E5: 7 | F5: 31 | G5: =COUNTIFS('2. Master'!$B$4:$B$162,$A5,'2. Master'!$O$4:$O$162,"Done") -> 4 | H5: =IFERROR($G5/$F5,0) -> 0.12903226 | I5: 2. Background document
A6: Strategy document - PHC | B6: Apresentada ao TWG-PHC; posição registada sobre cada área priorizada (aceite/alterada/rejeitada); ata com decisões e responsáveis; MINSA confirma que serve de documento de política habilitante; alterações acordadas incorporadas em versão datada | C6: 46346 | D6: Não iniciada | E6: 3 | F6: 9 | G6: =COUNTIFS('2. Master'!$B$4:$B$162,$A6,'2. Master'!$O$4:$O$162,"Done") -> 0 | H6: =IFERROR($G6/$F6,0) -> 0 | I6: 3. Strategy document
A7: HHFA e diagnóstico situacional | B7: Relatório do HHFA apresentado e aceite; mecanismo rotineiro de avaliação estrutural proposto ao MINSA | C7: 46542 | D7: Não iniciada | E7: 7 | F7: 22 | G7: =COUNTIFS('2. Master'!$B$4:$B$162,$A7,'2. Master'!$O$4:$O$162,"Done") -> 0 | H7: =IFERROR($G7/$F7,0) -> 0 | I7: 4. HHFA
A8: PFM | B8: Diagnóstico apresentado ao TWG-PFM; posição registada; ata com decisões; alterações incorporadas em versão datada | C8: 46444 | D8: Não iniciada | E8: 4 | F8: 20 | G8: =COUNTIFS('2. Master'!$B$4:$B$162,$A8,'2. Master'!$O$4:$O$162,"Done") -> 2 | H8: =IFERROR($G8/$F8,0) -> 0.1 | I8: 5. PFM
A9: Investment case - PHC | B9: Duas validações: diálogo no MINSA com a Ministra sobre a v1 (06/11/2026); validação técnica da v2, com HHFA, pelo TWG-PHC (26/02/2027) | C9: 46444 | D9: Não iniciada | E9: 4 | F9: 13 | G9: =COUNTIFS('2. Master'!$B$4:$B$162,$A9,'2. Master'!$O$4:$O$162,"Done") -> 0 | H9: =IFERROR($G9/$F9,0) -> 0 | I9: 6. Investment case
A10: PHC investment plan (custeado) | B10: Plano validado pelo TWG-PHC; posição registada; alterações incorporadas em versão datada | C10: 46472 | D10: Não iniciada | E10: 5 | F10: 15 | G10: =COUNTIFS('2. Master'!$B$4:$B$162,$A10,'2. Master'!$O$4:$O$162,"Done") -> 0 | H10: =IFERROR($G10/$F10,0) -> 0 | I10: 7. Investment plan
A11: Essential package - PHC | B11: Pacote essencial apresentado ao TWG-PHC; posição registada; alterações incorporadas em versão datada | C11: 46402 | D11: Não iniciada | E11: 4 | F11: 9 | G11: =COUNTIFS('2. Master'!$B$4:$B$162,$A11,'2. Master'!$O$4:$O$162,"Done") -> 0 | H11: =IFERROR($G11/$F11,0) -> 0 | I11: 8. Essential package
A12: Modelo de cuidados e perfis profissionais - PHC | B12: Modelo apresentado ao TWG-PHC; posição registada; alterações incorporadas em versão datada | C12: 46402 | D12: Não iniciada | E12: 4 | F12: 13 | G12: =COUNTIFS('2. Master'!$B$4:$B$162,$A12,'2. Master'!$O$4:$O$162,"Done") -> 0 | H12: =IFERROR($G12/$F12,0) -> 0 | I12: 9. Modelo de cuidados
A13: Project scoping - PHC | B13: Project profiles revistos com o MINSA e os financiadores potenciais | C13: 46500 | D13: Não iniciada | E13: 2 | F13: 6 | G13: =COUNTIFS('2. Master'!$B$4:$B$162,$A13,'2. Master'!$O$4:$O$162,"Done") -> 0 | H13: =IFERROR($G13/$F13,0) -> 0 | I13: 10. Project scoping
A14: Mobilização de financiamento - PHC | B14: Compromissos de financiadores registados; proposta de empréstimo assinada | C14: 46556 | D14: Não iniciada | E14: 2 | F14: 8 | G14: =COUNTIFS('2. Master'!$B$4:$B$162,$A14,'2. Master'!$O$4:$O$162,"Done") -> 0 | H14: =IFERROR($G14/$F14,0) -> 0 | I14: 11. Financiamento
A15: Relatórios contratuais do HIIP | E15: 2 | F15: 5 | G15: =COUNTIFS('2. Master'!$B$4:$B$162,$A15,'2. Master'!$O$4:$O$162,"Done") -> 0 | H15: =IFERROR($G15/$F15,0) -> 0 | I15: 12. Relatórios
A16: TOTAL | E16: =SUM(E4:E15) -> 45 | F16: =SUM(F4:F15) -> 159 | G16: =SUM(G4:G15) -> 6 | H16: =IFERROR(G16/F16,0) -> 0.037735849

Sheet 2. Master
A1: Master - todas as frentes, resultados e tarefas do HIIP
A3: Projeto | B3: Frente de trabalho (produto) | C3: Validação externa | D3: Data validação | E3: Estado validação | F3: Resultado (output) | G3: Definição de feito (resultado) | H3: Data resultado | I3: Estado resultado | J3: Tarefa | K3: Sprint | L3: Responsável | M3: Estimativa (dias) | N3: Depende de | O3: Estado tarefa | P3: Aprendizado
A4: HIIP | B4: TWG-PHC | C4: Autoridades autorizam formalmente a reconstituição do grupo; sessão de refundação realizada com quórum; plano de atividades aceite pelos membros | D4: 46318 | E4: Não iniciada | F4: Proposta de reconstituição do TWG-PHC | G4: Lista de atores anteriores identificada; lacunas de representação identificadas; plano de atividades redigido; convites e pedido de autorização preparados | H4: 46304 | I4: Não iniciado | J4: Identificar os atores anteriormente convocados | K4: S3 | L4: AGJ | M4: 2 | O4: Backlog
A5: HIIP | B5: TWG-PHC | C5: Autoridades autorizam formalmente a reconstituição do grupo; sessão de refundação realizada com quórum; plano de atividades aceite pelos membros | D5: 46318 | E5: Não iniciada | F5: Proposta de reconstituição do TWG-PHC | G5: Lista de atores anteriores identificada; lacunas de representação identificadas; plano de atividades redigido; convites e pedido de autorização preparados | H5: 46304 | I5: Não iniciado | J5: Identificar que atores faltam convocar | K5: S3 | L5: AGJ | M5: 1 | N5: Atores anteriores identificados | O5: Backlog
A6: HIIP | B6: TWG-PHC | C6: Autoridades autorizam formalmente a reconstituição do grupo; sessão de refundação realizada com quórum; plano de atividades aceite pelos membros | D6: 46318 | E6: Não iniciada | F6: Proposta de reconstituição do TWG-PHC | G6: Lista de atores anteriores identificada; lacunas de representação identificadas; plano de atividades redigido; convites e pedido de autorização preparados | H6: 46304 | I6: Não iniciado | J6: Planear as atividades do grupo de trabalho | K6: S4 | L6: AGJ | M6: 3 | N6: Lista de atores | O6: Backlog
A7: HIIP | B7: TWG-PHC | C7: Autoridades autorizam formalmente a reconstituição do grupo; sessão de refundação realizada com quórum; plano de atividades aceite pelos membros | D7: 46318 | E7: Não iniciada | F7: Proposta de reconstituição do TWG-PHC | G7: Lista de atores anteriores identificada; lacunas de representação identificadas; plano de atividades redigido; convites e pedido de autorização preparados | H7: 46304 | I7: Não iniciado | J7: Preparar o pedido de autorização às autoridades | K7: S5 | L7: AGJ | M7: 1 | N7: Plano de atividades | O7: Backlog
A8: HIIP | B8: TWG-PHC | C8: Autoridades autorizam formalmente a reconstituição do grupo; sessão de refundação realizada com quórum; plano de atividades aceite pelos membros | D8: 46318 | E8: Não iniciada | J8: Obter autorização formal das autoridades | K8: S5 | L8: AGJ | M8: 2 | N8: Pedido de autorização; anuência da DNSP | O8: Backlog
A9: HIIP | B9: TWG-PHC | C9: Autoridades autorizam formalmente a reconstituição do grupo; sessão de refundação realizada com quórum; plano de atividades aceite pelos membros | D9: 46318 | E9: Não iniciada | J9: Convidar as autoridades e os membros | K9: S6 | L9: AGJ | M9: 1 | N9: Autorização formal | O9: Backlog
A10: HIIP | B10: TWG-PHC | C10: Autoridades autorizam formalmente a reconstituição do grupo; sessão de refundação realizada com quórum; plano de atividades aceite pelos membros | D10: 46318 | E10: Não iniciada | J10: Agendar o encontro com todos | K10: S6 | L10: AGJ | M10: 1 | N10: Convites enviados | O10: Backlog
A11: HIIP | B11: TWG-PHC | C11: Autoridades autorizam formalmente a reconstituição do grupo; sessão de refundação realizada com quórum; plano de atividades aceite pelos membros | D11: 46318 | E11: Não iniciada | J11: Conduzir a sessão de refundação do grupo | K11: S6 | L11: AGJ | M11: 1 | N11: Encontro agendado | O11: Backlog
A12: HIIP | B12: Background document - PHC | C12: Apresentado ao TWG-PHC; posição registada sobre o diagnóstico; ata com comentários e responsáveis; alterações incorporadas em versão datada | D12: 46332 | E12: Não iniciada | F12: Auditoria do trabalho anterior das consultoras | G12: Metodologia previamente aplicada identificada; inventário dos dados recolhidos e dos que faltam; registo do que foi prometido ao cliente, com prazos e produtos; lacunas listadas | H12: 46262 | I12: Feito | J12: Reuniões com as consultoras | K12: S1 | L12: AGJ | M12: 2 | O12: Done
A13: HIIP | B13: Background document - PHC | C13: Apresentado ao TWG-PHC; posição registada sobre o diagnóstico; ata com comentários e responsáveis; alterações incorporadas em versão datada | D13: 46332 | E13: Não iniciada | F13: Auditoria do trabalho anterior das consultoras | G13: Metodologia previamente aplicada identificada; inventário dos dados recolhidos e dos que faltam; registo do que foi prometido ao cliente, com prazos e produtos; lacunas listadas | H13: 46262 | I13: Feito | J13: Identificação da metodologia previamente aplicada | K13: S1 | L13: AGJ | M13: 2 | O13: Done
A14: HIIP | B14: Background document - PHC | C14: Apresentado ao TWG-PHC; posição registada sobre o diagnóstico; ata com comentários e responsáveis; alterações incorporadas em versão datada | D14: 46332 | E14: Não iniciada | F14: Auditoria do trabalho anterior das consultoras | G14: Metodologia previamente aplicada identificada; inventário dos dados recolhidos e dos que faltam; registo do que foi prometido ao cliente, com prazos e produtos; lacunas listadas | H14: 46262 | I14: Feito | J14: Inventário dos dados recolhidos e dos que faltam recolher | K14: S2 | L14: AGJ | M14: 2 | O14: Done
A15: HIIP | B15: Background document - PHC | C15: Apresentado ao TWG-PHC; posição registada sobre o diagnóstico; ata com comentários e responsáveis; alterações incorporadas em versão datada | D15: 46332 | E15: Não iniciada | F15: Auditoria do trabalho anterior das consultoras | G15: Metodologia previamente aplicada identificada; inventário dos dados recolhidos e dos que faltam; registo do que foi prometido ao cliente, com prazos e produtos; lacunas listadas | H15: 46262 | I15: Feito | J15: Levantamento do que foi prometido ao cliente, com prazos e produtos | K15: S2 | L15: AGJ | M15: 2 | O15: Done
A16: HIIP | B16: Background document - PHC | C16: Apresentado ao TWG-PHC; posição registada sobre o diagnóstico; ata com comentários e responsáveis; alterações incorporadas em versão datada | D16: 46332 | E16: Não iniciada | F16: Estrutura analítica | G16: Documento estruturado pelas alavancas do operational framework; guias de entrevista mapeados nas alavancas; material das consultoras mapeado; forma de apresentação de barreiras, lacunas, gargalos e fortalezas definida | H16: 46276 | I16: Não iniciado | J16: Estruturar o documento pelas alavancas do operational framework | K16: S3 | L16: AGJ | M16: 2 | N16: Auditoria | O16: Backlog
A17: HIIP | B17: Background document - PHC | C17: Apresentado ao TWG-PHC; posição registada sobre o diagnóstico; ata com comentários e responsáveis; alterações incorporadas em versão datada | D17: 46332 | E17: Não iniciada | F17: Estrutura analítica | G17: Documento estruturado pelas alavancas do operational framework; guias de entrevista mapeados nas alavancas; material das consultoras mapeado; forma de apresentação de barreiras, lacunas, gargalos e fortalezas definida | H17: 46276 | I17: Não iniciado | J17: Reescrever os guias de entrevista mapeados nas alavancas | K17: S3 | L17: AGJ | M17: 3 | N17: Estrutura analítica | O17: Backlog
A18: HIIP | B18: Background document - PHC | C18: Apresentado ao TWG-PHC; posição registada sobre o diagnóstico; ata com comentários e responsáveis; alterações incorporadas em versão datada | D18: 46332 | E18: Não iniciada | F18: Estrutura analítica | G18: Documento estruturado pelas alavancas do operational framework; guias de entrevista mapeados nas alavancas; material das consultoras mapeado; forma de apresentação de barreiras, lacunas, gargalos e fortalezas definida | H18: 46276 | I18: Não iniciado | J18: Mapear o material das consultoras contra as alavancas | K18: S3 | L18: AGJ | M18: 2 | N18: Estrutura analítica | O18: Backlog
A19: HIIP | B19: Background document - PHC | C19: Apresentado ao TWG-PHC; posição registada sobre o diagnóstico; ata com comentários e responsáveis; alterações incorporadas em versão datada | D19: 46332 | E19: Não iniciada | F19: Estrutura analítica | G19: Documento estruturado pelas alavancas do operational framework; guias de entrevista mapeados nas alavancas; material das consultoras mapeado; forma de apresentação de barreiras, lacunas, gargalos e fortalezas definida | H19: 46276 | I19: Não iniciado | J19: Definir a forma de apresentação de barreiras, lacunas, gargalos e fortalezas | K19: S3 | L19: AGJ | M19: 1 | O19: Backlog
A20: HIIP | B20: Background document - PHC | C20: Apresentado ao TWG-PHC; posição registada sobre o diagnóstico; ata com comentários e responsáveis; alterações incorporadas em versão datada | D20: 46332 | E20: Não iniciada | F20: Espinha dorsal quantitativa | G20: Indicadores extraídos com data de extração; qualidade e completude avaliadas; anomalias listadas para interrogar no campo | H20: 46276 | I20: Não iniciado | J20: Extrair os indicadores do DHIS2 | K20: S3 | L20: AGJ | M20: 3 | O20: Backlog
A21: HIIP | B21: Background document - PHC | C21: Apresentado ao TWG-PHC; posição registada sobre o diagnóstico; ata com comentários e responsáveis; alterações incorporadas em versão datada | D21: 46332 | E21: Não iniciada | F21: Espinha dorsal quantitativa | G21: Indicadores extraídos com data de extração; qualidade e completude avaliadas; anomalias listadas para interrogar no campo | H21: 46276 | I21: Não iniciado | J21: Avaliar a qualidade e a completude dos dados extraídos | K21: S3 | L21: AGJ | M21: 2 | N21: Extração do DHIS2 | O21: Backlog
A22: HIIP | B22: Background document - PHC | C22: Apresentado ao TWG-PHC; posição registada sobre o diagnóstico; ata com comentários e responsáveis; alterações incorporadas em versão datada | D22: 46332 | E22: Não iniciada | F22: Espinha dorsal quantitativa | G22: Indicadores extraídos com data de extração; qualidade e completude avaliadas; anomalias listadas para interrogar no campo | H22: 46276 | I22: Não iniciado | J22: Identificar anomalias a interrogar no campo | K22: S3 | L22: AGJ | M22: 1 | N22: Avaliação de qualidade | O22: Backlog
A23: HIIP | B23: Background document - PHC | C23: Apresentado ao TWG-PHC; posição registada sobre o diagnóstico; ata com comentários e responsáveis; alterações incorporadas em versão datada | D23: 46332 | E23: Não iniciada | F23: Preparação das visitas piloto | G23: Anuência da DNSP registada; itens do HHFA selecionados com justificação; questionários testados no dispositivo antes da partida; lista de unidades e informantes acordada | H23: 46276 | I23: Não iniciado | J23: Pedir anuência à DNSP para as visitas e entrevistas piloto | K23: S3 | L23: AGJ | M23: 2 | O23: Backlog
A24: HIIP | B24: Background document - PHC | C24: Apresentado ao TWG-PHC; posição registada sobre o diagnóstico; ata com comentários e responsáveis; alterações incorporadas em versão datada | D24: 46332 | E24: Não iniciada | F24: Preparação das visitas piloto | G24: Anuência da DNSP registada; itens do HHFA selecionados com justificação; questionários testados no dispositivo antes da partida; lista de unidades e informantes acordada | H24: 46276 | I24: Não iniciado | J24: Selecionar do HHFA o que capturar neste piloto | K24: S3 | L24: AGJ | M24: 2 | O24: Backlog
A25: HIIP | B25: Background document - PHC | C25: Apresentado ao TWG-PHC; posição registada sobre o diagnóstico; ata com comentários e responsáveis; alterações incorporadas em versão datada | D25: 46332 | E25: Não iniciada | F25: Preparação das visitas piloto | G25: Anuência da DNSP registada; itens do HHFA selecionados com justificação; questionários testados no dispositivo antes da partida; lista de unidades e informantes acordada | H25: 46276 | I25: Não iniciado | J25: Preparar os questionários a partir do HHFA | K25: S3 | L25: AGJ | M25: 3 | N25: Seleção de itens do HHFA | O25: Backlog
A26: HIIP | B26: Background document - PHC | C26: Apresentado ao TWG-PHC; posição registada sobre o diagnóstico; ata com comentários e responsáveis; alterações incorporadas em versão datada | D26: 46332 | E26: Não iniciada | F26: Preparação das visitas piloto | G26: Anuência da DNSP registada; itens do HHFA selecionados com justificação; questionários testados no dispositivo antes da partida; lista de unidades e informantes acordada | H26: 46276 | I26: Não iniciado | J26: Carregar os questionários no KoboToolbox | K26: S3 | L26: AGJ | M26: 1 | N26: Questionários preparados | O26: Backlog
A27: HIIP | B27: Background document - PHC | C27: Apresentado ao TWG-PHC; posição registada sobre o diagnóstico; ata com comentários e responsáveis; alterações incorporadas em versão datada | D27: 46332 | E27: Não iniciada | F27: Preparação das visitas piloto | G27: Anuência da DNSP registada; itens do HHFA selecionados com justificação; questionários testados no dispositivo antes da partida; lista de unidades e informantes acordada | H27: 46276 | I27: Não iniciado | J27: Definir unidades, datas e perfis de informantes | K27: S3 | L27: AGJ | M27: 2 | N27: Anuência da DNSP | O27: Backlog
A28: HIIP | B28: Background document - PHC | C28: Apresentado ao TWG-PHC; posição registada sobre o diagnóstico; ata com comentários e responsáveis; alterações incorporadas em versão datada | D28: 46332 | E28: Não iniciada | F28: Visitas piloto realizadas | G28: Unidades previstas visitadas; dados sincronizados do Kobo; notas de entrevista transcritas; limitações do instrumento anotadas | H28: 46290 | I28: Não iniciado | J28: Conduzir as visitas às unidades sanitárias | K28: S4 | L28: AGJ | M28: 6 | N28: Preparação das visitas piloto | O28: Backlog
A29: HIIP | B29: Background document - PHC | C29: Apresentado ao TWG-PHC; posição registada sobre o diagnóstico; ata com comentários e responsáveis; alterações incorporadas em versão datada | D29: 46332 | E29: Não iniciada | F29: Visitas piloto realizadas | G29: Unidades previstas visitadas; dados sincronizados do Kobo; notas de entrevista transcritas; limitações do instrumento anotadas | H29: 46290 | I29: Não iniciado | J29: Conduzir entrevistas com profissionais e gestores locais, provinciais e nacionais | K29: S4 | L29: AGJ | M29: 4 | N29: Preparação das visitas piloto | O29: Backlog
A30: HIIP | B30: Background document - PHC | C30: Apresentado ao TWG-PHC; posição registada sobre o diagnóstico; ata com comentários e responsáveis; alterações incorporadas em versão datada | D30: 46332 | E30: Não iniciada | F30: Visitas piloto realizadas | G30: Unidades previstas visitadas; dados sincronizados do Kobo; notas de entrevista transcritas; limitações do instrumento anotadas | H30: 46290 | I30: Não iniciado | J30: Registar e organizar o material recolhido | K30: S4 | L30: AGJ | M30: 2 | N30: Visitas realizadas | O30: Backlog
A31: HIIP | B31: Background document - PHC | C31: Apresentado ao TWG-PHC; posição registada sobre o diagnóstico; ata com comentários e responsáveis; alterações incorporadas em versão datada | D31: 46332 | E31: Não iniciada | F31: Visitas piloto realizadas | G31: Unidades previstas visitadas; dados sincronizados do Kobo; notas de entrevista transcritas; limitações do instrumento anotadas | H31: 46290 | I31: Não iniciado | J31: Registar as lições do piloto para o desenho do HHFA | K31: S4 | L31: AGJ | M31: 1 | N31: Visitas realizadas | O31: Backlog
A32: HIIP | B32: Background document - PHC | C32: Apresentado ao TWG-PHC; posição registada sobre o diagnóstico; ata com comentários e responsáveis; alterações incorporadas em versão datada | D32: 46332 | E32: Não iniciada | F32: Síntese e mapeamento | G32: Achados codificados; barreiras, lacunas, gargalos e fortalezas classificados por estrutura, processo e resultado e mapeados nas alavancas; modelo de cuidados atual descrito; evidências dos informantes contrapostas à evidência científica atual | H32: 46304 | I32: Não iniciado | J32: Codificar e sintetizar os achados qualitativos | K32: S5 | L32: AGJ | M32: 4 | N32: Visitas piloto realizadas | O32: Backlog
A33: HIIP | B33: Background document - PHC | C33: Apresentado ao TWG-PHC; posição registada sobre o diagnóstico; ata com comentários e responsáveis; alterações incorporadas em versão datada | D33: 46332 | E33: Não iniciada | F33: Síntese e mapeamento | G33: Achados codificados; barreiras, lacunas, gargalos e fortalezas classificados por estrutura, processo e resultado e mapeados nas alavancas; modelo de cuidados atual descrito; evidências dos informantes contrapostas à evidência científica atual | H33: 46304 | I33: Não iniciado | J33: Mapear barreiras, lacunas, gargalos e fortalezas por estrutura, processo e resultado | K33: S5 | L33: AGJ | M33: 3 | N33: Síntese qualitativa | O33: Backlog
A34: HIIP | B34: Background document - PHC | C34: Apresentado ao TWG-PHC; posição registada sobre o diagnóstico; ata com comentários e responsáveis; alterações incorporadas em versão datada | D34: 46332 | E34: Não iniciada | F34: Síntese e mapeamento | G34: Achados codificados; barreiras, lacunas, gargalos e fortalezas classificados por estrutura, processo e resultado e mapeados nas alavancas; modelo de cuidados atual descrito; evidências dos informantes contrapostas à evidência científica atual | H34: 46304 | I34: Não iniciado | J34: Descrever o modelo de cuidados atual | K34: S5 | L34: AGJ | M34: 3 | N34: Síntese qualitativa | O34: Backlog
A35: HIIP | B35: Background document - PHC | C35: Apresentado ao TWG-PHC; posição registada sobre o diagnóstico; ata com comentários e responsáveis; alterações incorporadas em versão datada | D35: 46332 | E35: Não iniciada | F35: Síntese e mapeamento | G35: Achados codificados; barreiras, lacunas, gargalos e fortalezas classificados por estrutura, processo e resultado e mapeados nas alavancas; modelo de cuidados atual descrito; evidências dos informantes contrapostas à evidência científica atual | H35: 46304 | I35: Não iniciado | J35: Contrapor as evidências dos informantes à evidência científica atual | K35: S5 | L35: AGJ | M35: 3 | N35: Mapeamento | O35: Backlog
A36: HIIP | B36: Background document - PHC | C36: Apresentado ao TWG-PHC; posição registada sobre o diagnóstico; ata com comentários e responsáveis; alterações incorporadas em versão datada | D36: 46332 | E36: Não iniciada | F36: Background document v1 | G36: Forma de apresentação aplicada; secção de contraste escrita; linguagem adequada ao cliente; evidências e referências revistas; revisão do country office resolvida | H36: 46318 | I36: Não iniciado | J36: Redigir a secção de contraste entre o que se acredita e o que se observou | K36: S5 | L36: AGJ | M36: 2 | N36: Síntese e mapeamento | O36: Backlog
... A40: HIIP | B40: Background document - PHC | C40: Apresentado ao TWG-PHC; posição registada sobre o diagnóstico; ata com comentários e responsáveis; alterações incorporadas em versão datada | D40: 46332 | E40: Não iniciada | F40: Background document v1 | G40: Forma de apresentação aplicada; secção de contraste escrita; linguagem adequada ao cliente; evidências e referências revistas; revisão do country office resolvida | H40: 46318 | I40: Não iniciado | J40: Revisão do country office | K40: S6 | L40: AGJ | M40: 2 | N40: Background document v1 | O40: Backlog
A41: HIIP | B41: Background document - PHC | C41: Apresentado ao TWG-PHC; posição registada sobre o diagnóstico; ata com comentários e responsáveis; alterações incorporadas em versão datada | D41: 46332 | E41: Não iniciada | J41: Apresentar o documento ao TWG-PHC para validação | K41: S6 | L41: AGJ | M41: 1 | N41: TWG-PHC refundado; Background v1 | O41: Backlog
A42: HIIP | B42: Background document - PHC | C42: Apresentado ao TWG-PHC; posição registada sobre o diagnóstico; ata com comentários e responsáveis; alterações incorporadas em versão datada | D42: 46332 | E42: Não iniciada | J42: Incorporar os comentários do TWG-PHC | K42: S7 | L42: AGJ | M42: 2 | N42: Sessão de validação | O42: Backlog
A43: HIIP | B43: Strategy document - PHC | C43: Apresentada ao TWG-PHC; posição registada sobre cada área priorizada (aceite/alterada/rejeitada); ata com decisões e responsáveis; MINSA confirma que serve de documento de política habilitante; alterações acordadas incorporadas em versão datada | D43: 46346 | E43: Não iniciada | F43: Mapa de barreiras, lacunas, gargalos e fortalezas | G43: Itens classificados por estrutura, processo e resultado e mapeados nas alavancas do framework; cada item com fonte identificada; intervenções candidatas com referência e nível de evidência | H43: 46304 | I43: Não iniciado | J43: Mapear barreiras, lacunas, gargalos e fortalezas por estrutura, processo e resultado | K43: S5 | L43: AGJ | M43: 4 | N43: Síntese qualitativa do campo | O43: Backlog
A44: HIIP | B44: Strategy document - PHC | C44: Apresentada ao TWG-PHC; posição registada sobre cada área priorizada (aceite/alterada/rejeitada); ata com decisões e responsáveis; MINSA confirma que serve de documento de política habilitante; alterações acordadas incorporadas em versão datada | D44: 46346 | E44: Não iniciada | F44: Mapa de barreiras, lacunas, gargalos e fortalezas | G44: Itens classificados por estrutura, processo e resultado e mapeados nas alavancas do framework; cada item com fonte identificada; intervenções candidatas com referência e nível de evidência | H44: 46304 | I44: Não iniciado | J44: Rever evidência de intervenções para cada barreira, lacuna e gargalo | K44: S5 | L44: AGJ | M44: 5 | N44: Mapa de barreiras | O44: Backlog
A45: HIIP | B45: Strategy document - PHC | C45: Apresentada ao TWG-PHC; posição registada sobre cada área priorizada (aceite/alterada/rejeitada); ata com decisões e responsáveis; MINSA confirma que serve de documento de política habilitante; alterações acordadas incorporadas em versão datada | D45: 46346 | E45: Não iniciada | F45: Teoria da mudança e leque de opções | G45: Cadeia barreira > intervenção > resultado explícita; cada opção com custo relativo, tempo até efeito e pré-condições; alternativas descartadas com a razão; áreas e ações candidatas à priorização identificadas | H45: 46304 | I45: Não iniciado | J45: Desenhar a teoria da mudança | K45: S5 | L45: AGJ | M45: 3 | N45: Tabela de evidência | O45: Backlog
A46: HIIP | B46: Strategy document - PHC | C46: Apresentada ao TWG-PHC; posição registada sobre cada área priorizada (aceite/alterada/rejeitada); ata com decisões e responsáveis; MINSA confirma que serve de documento de política habilitante; alterações acordadas incorporadas em versão datada | D46: 46346 | E46: Não iniciada | F46: Teoria da mudança e leque de opções | G46: Cadeia barreira > intervenção > resultado explícita; cada opção com custo relativo, tempo até efeito e pré-condições; alternativas descartadas com a razão; áreas e ações candidatas à priorização identificadas | H46: 46304 | I46: Não iniciado | J46: Construir o leque de opções para debate | K46: S5 | L46: AGJ | M46: 3 | N46: Teoria da mudança | O46: Backlog
A47: HIIP | B47: Strategy document - PHC | C47: Apresentada ao TWG-PHC; posição registada sobre cada área priorizada (aceite/alterada/rejeitada); ata com decisões e responsáveis; MINSA confirma que serve de documento de política habilitante; alterações acordadas incorporadas em versão datada | D47: 46346 | E47: Não iniciada | F47: Teoria da mudança e leque de opções | G47: Cadeia barreira > intervenção > resultado explícita; cada opção com custo relativo, tempo até efeito e pré-condições; alternativas descartadas com a razão; áreas e ações candidatas à priorização identificadas | H47: 46304 | I47: Não iniciado | J47: Identificação de áreas e ações para priorização | K47: S5 | L47: AGJ | M47: 3 | N47: Leque de opções | O47: Backlog
A48: HIIP | B48: Strategy document - PHC | C48: Apresentada ao TWG-PHC; posição registada sobre cada área priorizada (aceite/alterada/rejeitada); ata com decisões e responsáveis; MINSA confirma que serve de documento de política habilitante; alterações acordadas incorporadas em versão datada | D48: 46346 | E48: Não iniciada | F48: Estratégia v1 com áreas priorizadas | G48: Cobre todas as alavancas do framework; cada recomendação rastreável a uma barreira e à sua evidência; critério de priorização explícito; revisão do country office resolvida; versão em português pronta | H48: 46318 | I48: Não iniciado | J48: Redigir a estratégia v1 | K48: S5 | L48: AGJ | M48: 5 | N48: Áreas e ações priorizadas | O48: Backlog
A49: HIIP | B49: Strategy document - PHC | C49: Apresentada ao TWG-PHC; posição registada sobre cada área priorizada (aceite/alterada/rejeitada); ata com decisões e responsáveis; MINSA confirma que serve de documento de política habilitante; alterações acordadas incorporadas em versão datada | D49: 46346 | E49: Não iniciada | F49: Estratégia v1 com áreas priorizadas | G49: Cobre todas as alavancas do framework; cada recomendação rastreável a uma barreira e à sua evidência; critério de priorização explícito; revisão do country office resolvida; versão em português pronta | H49: 46318 | I49: Não iniciado | J49: Revisão interna e pré-alinhamento com o MINSA | K49: S6 | L49: AGJ | M49: 2 | N49: Estratégia v1 | O49: Backlog
A50: HIIP | B50: Strategy document - PHC | C50: Apresentada ao TWG-PHC; posição registada sobre cada área priorizada (aceite/alterada/rejeitada); ata com decisões e responsáveis; MINSA confirma que serve de documento de política habilitante; alterações acordadas incorporadas em versão datada | D50: 46346 | E50: Não iniciada | J50: Conduzir o policy dialogue de validação | K50: S7 | L50: AGJ | M50: 2 | N50: TWG-PHC refundado; Estratégia v1 | O50: Backlog
A51: HIIP | B51: Strategy document - PHC | C51: Apresentada ao TWG-PHC; posição registada sobre cada área priorizada (aceite/alterada/rejeitada); ata com decisões e responsáveis; MINSA confirma que serve de documento de política habilitante; alterações acordadas incorporadas em versão datada | D51: 46346 | E51: Não iniciada | J51: Incorporar as alterações acordadas | K51: S8 | L51: AGJ | M51: 3 | N51: Policy dialogue | O51: Backlog
A52: HIIP | B52: HHFA e diagnóstico situacional | C52: Relatório do HHFA apresentado e aceite; mecanismo rotineiro de avaliação estrutural proposto ao MINSA | D52: 46542 | E52: Não iniciada | F52: Acordo interagências | G52: Âmbito partilhado acordado; divisão de custos definida; acordo de cofinanciamento formalizado | H52: 46304 | I52: Em curso | J52: Manter as reuniões de alinhamento com o UNICEF e o UNFPA | K52: S3 | L52: AGJ | M52: 2 | O52: In progress
A53: HIIP | B53: HHFA e diagnóstico situacional | C53: Relatório do HHFA apresentado e aceite; mecanismo rotineiro de avaliação estrutural proposto ao MINSA | D53: 46542 | E53: Não iniciada | F53: Acordo interagências | G53: Âmbito partilhado acordado; divisão de custos definida; acordo de cofinanciamento formalizado | H53: 46304 | I53: Em curso | J53: Definir o âmbito partilhado e a divisão de custos | K53: S4 | L53: AGJ | M53: 2 | N53: Reuniões de alinhamento | O53: Backlog
A54: HIIP | B54: HHFA e diagnóstico situacional | C54: Relatório do HHFA apresentado e aceite; mecanismo rotineiro de avaliação estrutural proposto ao MINSA | D54: 46542 | E54: Não iniciada | F54: Acordo interagências | G54: Âmbito partilhado acordado; divisão de custos definida; acordo de cofinanciamento formalizado | H54: 46304 | I54: Em curso | J54: Formalizar o acordo de cofinanciamento | K54: S5 | L54: AGJ | M54: 2 | N54: Âmbito e custos definidos | O54: Backlog
A55: HIIP | B55: HHFA e diagnóstico situacional | C55: Relatório do HHFA apresentado e aceite; mecanismo rotineiro de avaliação estrutural proposto ao MINSA | D55: 46542 | E55: Não iniciada | F55: Adesão ao inquérito já contratado | G55: Amostra e ToR obtidos e analisados; lacunas face às perguntas do HIIP identificadas por escrito; margem de inclusão de itens confirmada com o UNFPA; cronograma de recolha conhecido e registado | H55: 46276 | I55: Não iniciado | J55: Obter e rever a amostragem, o ToR e o contrato já decididos | K55: S3 | L55: AGJ | M55: 1 | O55: Backlog
A56: HIIP | B56: HHFA e diagnóstico situacional | C56: Relatório do HHFA apresentado e aceite; mecanismo rotineiro de avaliação estrutural proposto ao MINSA | D56: 46542 | E56: Não iniciada | F56: Adesão ao inquérito já contratado | G56: Amostra e ToR obtidos e analisados; lacunas face às perguntas do HIIP identificadas por escrito; margem de inclusão de itens confirmada com o UNFPA; cronograma de recolha conhecido e registado | H56: 46276 | I56: Não iniciado | J56: Avaliar se a amostra serve às perguntas do diagnóstico dos CSP | K56: S3 | L56: AGJ | M56: 2 | N56: Amostragem obtida | O56: Backlog
A57: HIIP | B57: HHFA e diagnóstico situacional | C57: Relatório do HHFA apresentado e aceite; mecanismo rotineiro de avaliação estrutural proposto ao MINSA | D57: 46542 | E57: Não iniciada | F57: Adesão ao inquérito já contratado | G57: Amostra e ToR obtidos e analisados; lacunas face às perguntas do HIIP identificadas por escrito; margem de inclusão de itens confirmada com o UNFPA; cronograma de recolha conhecido e registado | H57: 46276 | I57: Não iniciado | J57: Identificar que margem existe para acrescentar itens ao instrumento | K57: S3 | L57: AGJ | M57: 1 | N57: Avaliação da amostra | O57: Backlog
A58: HIIP | B58: HHFA e diagnóstico situacional | C58: Relatório do HHFA apresentado e aceite; mecanismo rotineiro de avaliação estrutural proposto ao MINSA | D58: 46542 | E58: Não iniciada | F58: Adesão ao inquérito já contratado | G58: Amostra e ToR obtidos e analisados; lacunas face às perguntas do HIIP identificadas por escrito; margem de inclusão de itens confirmada com o UNFPA; cronograma de recolha conhecido e registado | H58: 46276 | I58: Não iniciado | J58: Participar na reunião de arranque com a empresa contratada | K58: S3 | L58: AGJ | M58: 1 | O58: Backlog
A59: HIIP | B59: HHFA e diagnóstico situacional | C59: Relatório do HHFA apresentado e aceite; mecanismo rotineiro de avaliação estrutural proposto ao MINSA | D59: 46542 | E59: Não iniciada | F59: Adesão ao inquérito já contratado | G59: Amostra e ToR obtidos e analisados; lacunas face às perguntas do HIIP identificadas por escrito; margem de inclusão de itens confirmada com o UNFPA; cronograma de recolha conhecido e registado | H59: 46276 | I59: Não iniciado | J59: Alinhar o cronograma de recolha com o calendário do HIIP | K59: S3 | L59: AGJ | M59: 1 | N59: Reunião de arranque | O59: Backlog
A60: HIIP | B60: HHFA e diagnóstico situacional | C60: Relatório do HHFA apresentado e aceite; mecanismo rotineiro de avaliação estrutural proposto ao MINSA | D60: 46542 | E60: Não iniciada | F60: Seleção de itens | G60: Itens do HHFA para o piloto selecionados com justificação; lista de itens sumários de estrutura, processo e resultado definida a partir do piloto | H60: 46304 | I60: Não iniciado | J60: Selecionar do HHFA os itens a capturar no piloto | K60: S3 | L60: AGJ | M60: 2 | N60: Margem de inclusão confirmada | O60: Backlog
A61: HIIP | B61: HHFA e diagnóstico situacional | C61: Relatório do HHFA apresentado e aceite; mecanismo rotineiro de avaliação estrutural proposto ao MINSA | D61: 46542 | E61: Não iniciada | F61: Seleção de itens | G61: Itens do HHFA para o piloto selecionados com justificação; lista de itens sumários de estrutura, processo e resultado definida a partir do piloto | H61: 46304 | I61: Não iniciado | J61: Definir a lista de itens sumários a partir do piloto | K61: S5 | L61: AGJ | M61: 3 | N61: Visitas piloto realizadas | O61: Backlog
A62: HIIP | B62: HHFA e diagnóstico situacional | C62: Relatório do HHFA apresentado e aceite; mecanismo rotineiro de avaliação estrutural proposto ao MINSA | D62: 46542 | E62: Não iniciada | F62: Instrumento | G62: Instrumento adaptado ao contexto angolano; programado no Kobo; pré-testado; desenho de métodos mistos sequencial exploratório documentado | H62: 46318 | I62: Não iniciado | J62: Adaptar o instrumento HHFA ao contexto angolano | K62: S6 | L62: AGJ | M62: 4 | N62: Lista de itens sumários | O62: Backlog
A63: HIIP | B63: HHFA e diagnóstico situacional | C63: Relatório do HHFA apresentado e aceite; mecanismo rotineiro de avaliação estrutural proposto ao MINSA | D63: 46542 | E63: Não iniciada | F63: Instrumento | G63: Instrumento adaptado ao contexto angolano; programado no Kobo; pré-testado; desenho de métodos mistos sequencial exploratório documentado | H63: 46318 | I63: Não iniciado | J63: Programar o instrumento no KoboToolbox | K63: S6 | L63: AGJ | M63: 2 | N63: Instrumento adaptado | O63: Backlog
A64: HIIP | B64: HHFA e diagnóstico situacional | C64: Relatório do HHFA apresentado e aceite; mecanismo rotineiro de avaliação estrutural proposto ao MINSA | D64: 46542 | E64: Não iniciada | F64: Instrumento | G64: Instrumento adaptado ao contexto angolano; programado no Kobo; pré-testado; desenho de métodos mistos sequencial exploratório documentado | H64: 46318 | I64: Não iniciado | J64: Pré-testar o instrumento | K64: S6 | L64: AGJ | M64: 1 | N64: Instrumento programado | O64: Backlog
A65: HIIP | B65: HHFA e diagnóstico situacional | C65: Relatório do HHFA apresentado e aceite; mecanismo rotineiro de avaliação estrutural proposto ao MINSA | D65: 46542 | E65: Não iniciada | F65: Instrumento | G65: Instrumento adaptado ao contexto angolano; programado no Kobo; pré-testado; desenho de métodos mistos sequencial exploratório documentado | H65: 46318 | I65: Não iniciado | J65: Documentar o desenho de métodos mistos sequencial exploratório | K65: S6 | L65: AGJ | M65: 2 | O65: Backlog
A66: HIIP | B66: HHFA e diagnóstico situacional | C66: Relatório do HHFA apresentado e aceite; mecanismo rotineiro de avaliação estrutural proposto ao MINSA | D66: 46542 | E66: Não iniciada | F66: Recolha | G66: Formação dos inquiridores acompanhada; recolha em curso conforme cronograma; qualidade monitorizada por vaga | H66: 46374 | I66: Não iniciado | J66: Acompanhar a formação dos inquiridores da empresa | K66: S7 | L66: AGJ | M66: 2 | N66: Instrumento pré-testado | O66: Backlog
A67: HIIP | B67: HHFA e diagnóstico situacional | C67: Relatório do HHFA apresentado e aceite; mecanismo rotineiro de avaliação estrutural proposto ao MINSA | D67: 46542 | E67: Não iniciada | F67: Recolha | G67: Formação dos inquiridores acompanhada; recolha em curso conforme cronograma; qualidade monitorizada por vaga | H67: 46374 | I67: Não iniciado | J67: Acompanhar a logística de terreno | K67: S7 | L67: AGJ | M67: 1 | O67: Backlog
A68: HIIP | B68: HHFA e diagnóstico situacional | C68: Relatório do HHFA apresentado e aceite; mecanismo rotineiro de avaliação estrutural proposto ao MINSA | D68: 46542 | E68: Não iniciada | F68: Recolha | G68: Formação dos inquiridores acompanhada; recolha em curso conforme cronograma; qualidade monitorizada por vaga | H68: 46374 | I68: Não iniciado | J68: Monitorizar a qualidade dos dados por vaga | K68: Recorrente | L68: AGJ | M68: 1 | N68: Recolha em curso | O68: Backlog
A69: HIIP | B69: HHFA e diagnóstico situacional | C69: Relatório do HHFA apresentado e aceite; mecanismo rotineiro de avaliação estrutural proposto ao MINSA | D69: 46542 | E69: Não iniciada | F69: Análise | G69: Base limpa e documentada; análise concluída; relatório do HHFA redigido | H69: 46430 | I69: Não iniciado | J69: Limpar e organizar a base de dados | K69: S12 | L69: AGJ | M69: 3 | N69: Recolha concluída | O69: Backlog
A70: HIIP | B70: HHFA e diagnóstico situacional | C70: Relatório do HHFA apresentado e aceite; mecanismo rotineiro de avaliação estrutural proposto ao MINSA | D70: 46542 | E70: Não iniciada | F70: Análise | G70: Base limpa e documentada; análise concluída; relatório do HHFA redigido | H70: 46430 | I70: Não iniciado | J70: Analisar os dados | K70: S12 | L70: AGJ | M70: 5 | N70: Base limpa | O70: Backlog
A71: HIIP | B71: HHFA e diagnóstico situacional | C71: Relatório do HHFA apresentado e aceite; mecanismo rotineiro de avaliação estrutural proposto ao MINSA | D71: 46542 | E71: Não iniciada | F71: Análise | G71: Base limpa e documentada; análise concluída; relatório do HHFA redigido | H71: 46430 | I71: Não iniciado | J71: Redigir o relatório do HHFA | K71: S13 | L71: AGJ | M71: 5 | N71: Análise | O71: Backlog
A72: HIIP | B72: HHFA e diagnóstico situacional | C72: Relatório do HHFA apresentado e aceite; mecanismo rotineiro de avaliação estrutural proposto ao MINSA | D72: 46542 | E72: Não iniciada | F72: Legado | G72: Mecanismo rotineiro de avaliação estrutural desenhado; proposta submetida ao MINSA | H72: 46542 | I72: Não iniciado | J72: Desenhar o mecanismo rotineiro de avaliação estrutural | K72: S13 | L72: AGJ | M72: 4 | N72: Relatório do HHFA | O72: Backlog
A73: HIIP | B73: HHFA e diagnóstico situacional | C73: Relatório do HHFA apresentado e aceite; mecanismo rotineiro de avaliação estrutural proposto ao MINSA | D73: 46542 | E73: Não iniciada | F73: Legado | G73: Mecanismo rotineiro de avaliação estrutural desenhado; proposta submetida ao MINSA | H73: 46542 | I73: Não iniciado | J73: Propor o mecanismo ao MINSA | K73: S14 | L73: AGJ | M73: 2 | N73: Mecanismo desenhado | O73: Backlog
A74: HIIP | B74: PFM | C74: Diagnóstico apresentado ao TWG-PFM; posição registada; ata com decisões; alterações incorporadas em versão datada | D74: 46444 | E74: Não iniciada | F74: TWG-PFM constituído | G74: ToR aprovado pelo MINSA; lista de membros confirmada; relatório das entrevistas partilhado; ata da sessão inaugural com plano de trabalho acordado | H74: 46290 | I74: Em curso | J74: Finalizar o ToR do TWG-PFM | K74: S1 | L74: AGJ | M74: 2 | O74: Done
A75: HIIP | B75: PFM | C75: Diagnóstico apresentado ao TWG-PFM; posição registada; ata com decisões; alterações incorporadas em versão datada | D75: 46444 | E75: Não iniciada | F75: TWG-PFM constituído | G75: ToR aprovado pelo MINSA; lista de membros confirmada; relatório das entrevistas partilhado; ata da sessão inaugural com plano de trabalho acordado | H75: 46290 | I75: Em curso | J75: Confirmar a lista de participantes | K75: S2 | L75: AGJ | M75: 2 | N75: ToR | O75: Done
A76: HIIP | B76: PFM | C76: Diagnóstico apresentado ao TWG-PFM; posição registada; ata com decisões; alterações incorporadas em versão datada | D76: 46444 | E76: Não iniciada | F76: TWG-PFM constituído | G76: ToR aprovado pelo MINSA; lista de membros confirmada; relatório das entrevistas partilhado; ata da sessão inaugural com plano de trabalho acordado | H76: 46290 | I76: Em curso | J76: Organizar o cronograma e enviar os convites | K76: S3 | L76: AGJ | M76: 2 | N76: Lista de participantes | O76: In progress
A77: HIIP | B77: PFM | C77: Diagnóstico apresentado ao TWG-PFM; posição registada; ata com decisões; alterações incorporadas em versão datada | D77: 46444 | E77: Não iniciada | F77: TWG-PFM constituído | G77: ToR aprovado pelo MINSA; lista de membros confirmada; relatório das entrevistas partilhado; ata da sessão inaugural com plano de trabalho acordado | H77: 46290 | I77: Em curso | J77: Conduzir as entrevistas preparatórias com os membros | K77: S3 | L77: AGJ | M77: 4 | N77: Convites | O77: Backlog
A78: HIIP | B78: PFM | C78: Diagnóstico apresentado ao TWG-PFM; posição registada; ata com decisões; alterações incorporadas em versão datada | D78: 46444 | E78: Não iniciada | F78: TWG-PFM constituído | G78: ToR aprovado pelo MINSA; lista de membros confirmada; relatório das entrevistas partilhado; ata da sessão inaugural com plano de trabalho acordado | H78: 46290 | I78: Em curso | J78: Produzir o relatório das entrevistas preparatórias | K78: S4 | L78: AGJ | M78: 3 | N78: Entrevistas preparatórias | O78: Backlog
A79: HIIP | B79: PFM | C79: Diagnóstico apresentado ao TWG-PFM; posição registada; ata com decisões; alterações incorporadas em versão datada | D79: 46444 | E79: Não iniciada | F79: TWG-PFM constituído | G79: ToR aprovado pelo MINSA; lista de membros confirmada; relatório das entrevistas partilhado; ata da sessão inaugural com plano de trabalho acordado | H79: 46290 | I79: Em curso | J79: Conduzir a sessão inaugural | K79: S4 | L79: AGJ | M79: 1 | N79: Relatório das entrevistas | O79: Backlog
A80: HIIP | B80: PFM | C80: Diagnóstico apresentado ao TWG-PFM; posição registada; ata com decisões; alterações incorporadas em versão datada | D80: 46444 | E80: Não iniciada | F80: TWG-PFM constituído | G80: ToR aprovado pelo MINSA; lista de membros confirmada; relatório das entrevistas partilhado; ata da sessão inaugural com plano de trabalho acordado | H80: 46290 | I80: Em curso | J80: Acordar o plano de trabalho e o calendário quinzenal | K80: S4 | L80: AGJ | M80: 1 | N80: Sessão inaugural | O80: Backlog
A81: HIIP | B81: PFM | C81: Diagnóstico apresentado ao TWG-PFM; posição registada; ata com decisões; alterações incorporadas em versão datada | D81: 46444 | E81: Não iniciada | F81: Consultoria PFM contratada | G81: ToR aprovado; contrato assinado; especialista local integrado; relatório de arranque aceite | H81: 46332 | I81: Não iniciado | J81: Reunião com o Banco Mundial sobre o financiamento do especialista local | K81: S3 | L81: AGJ | M81: 1 | O81: Backlog
A82: HIIP | B82: PFM | C82: Diagnóstico apresentado ao TWG-PFM; posição registada; ata com decisões; alterações incorporadas em versão datada | D82: 46444 | E82: Não iniciada | F82: Consultoria PFM contratada | G82: ToR aprovado; contrato assinado; especialista local integrado; relatório de arranque aceite | H82: 46332 | I82: Não iniciado | J82: Redigir o ToR e as especificações da consultoria | K82: S4 | L82: AGJ | M82: 3 | N82: Relatório das entrevistas | O82: Backlog
A83: HIIP | B83: PFM | C83: Diagnóstico apresentado ao TWG-PFM; posição registada; ata com decisões; alterações incorporadas em versão datada | D83: 46444 | E83: Não iniciada | F83: Consultoria PFM contratada | G83: ToR aprovado; contrato assinado; especialista local integrado; relatório de arranque aceite | H83: 46332 | I83: Não iniciado | J83: Conduzir o processo de seleção | K83: S5 | L83: AGJ | M83: 5 | N83: ToR da consultoria | O83: Backlog
A84: HIIP | B84: PFM | C84: Diagnóstico apresentado ao TWG-PFM; posição registada; ata com decisões; alterações incorporadas em versão datada | D84: 46444 | E84: Não iniciada | F84: Consultoria PFM contratada | G84: ToR aprovado; contrato assinado; especialista local integrado; relatório de arranque aceite | H84: 46332 | I84: Não iniciado | J84: Contratar a consultoria | K84: S6 | L84: AGJ | M84: 2 | N84: Processo de seleção | O84: Backlog
A85: HIIP | B85: PFM | C85: Diagnóstico apresentado ao TWG-PFM; posição registada; ata com decisões; alterações incorporadas em versão datada | D85: 46444 | E85: Não iniciada | F85: Consultoria PFM contratada | G85: ToR aprovado; contrato assinado; especialista local integrado; relatório de arranque aceite | H85: 46332 | I85: Não iniciado | J85: Integrar o especialista local | K85: S6 | L85: AGJ | M85: 3 | N85: Acordo com o Banco Mundial | O85: Backlog
A86: HIIP | B86: PFM | C86: Diagnóstico apresentado ao TWG-PFM; posição registada; ata com decisões; alterações incorporadas em versão datada | D86: 46444 | E86: Não iniciada | F86: Consultoria PFM contratada | G86: ToR aprovado; contrato assinado; especialista local integrado; relatório de arranque aceite | H86: 46332 | I86: Não iniciado | J86: Reunião de arranque e validação do plano de trabalho | K86: S7 | L86: AGJ | M86: 2 | N86: Contrato assinado | O86: Backlog
A87: HIIP | B87: PFM | C87: Diagnóstico apresentado ao TWG-PFM; posição registada; ata com decisões; alterações incorporadas em versão datada | D87: 46444 | E87: Não iniciada | F87: Condução da consultoria | G87: Reuniões quinzenais realizadas com ata; primeiro rascunho revisto; relatório final aceite | H87: 46430 | I87: Não iniciado | J87: Conduzir as reuniões quinzenais do TWG-PFM | K87: Recorrente | L87: AGJ | M87: 1 | N87: Sessão inaugural | O87: Backlog
A88: HIIP | B88: PFM | C88: Diagnóstico apresentado ao TWG-PFM; posição registada; ata com decisões; alterações incorporadas em versão datada | D88: 46444 | E88: Não iniciada | F88: Condução da consultoria | G88: Reuniões quinzenais realizadas com ata; primeiro rascunho revisto; relatório final aceite | H88: 46430 | I88: Não iniciado | J88: Supervisionar as entrevistas e atividades com o grupo | K88: Recorrente | L88: AGJ | M88: 2 | N88: Reunião de arranque | O88: Backlog
A89: HIIP | B89: PFM | C89: Diagnóstico apresentado ao TWG-PFM; posição registada; ata com decisões; alterações incorporadas em versão datada | D89: 46444 | E89: Não iniciada | F89: Condução da consultoria | G89: Reuniões quinzenais realizadas com ata; primeiro rascunho revisto; relatório final aceite | H89: 46430 | I89: Não iniciado | J89: Rever o primeiro rascunho da consultoria | K89: S9 | L89: AGJ | M89: 2 | N89: Consultoria em curso | O89: Backlog
A90: HIIP | B90: PFM | C90: Diagnóstico apresentado ao TWG-PFM; posição registada; ata com decisões; alterações incorporadas em versão datada | D90: 46444 | E90: Não iniciada | F90: Condução da consultoria | G90: Reuniões quinzenais realizadas com ata; primeiro rascunho revisto; relatório final aceite | H90: 46430 | I90: Não iniciado | J90: Rever e aceitar o relatório final | K90: S13 | L90: AGJ | M90: 3 | N90: Primeiro rascunho | O90: Backlog
A91: HIIP | B91: PFM | C91: Diagnóstico apresentado ao TWG-PFM; posição registada; ata com decisões; alterações incorporadas em versão datada | D91: 46444 | E91: Não iniciada | F91: Alinhamento com parceiros | G91: Divisão de trabalho documentada com o UNDP e o Banco Mundial | H91: 46346 | I91: Não iniciado | J91: Alinhar com o UNDP e o Banco Mundial sobre as frentes de modernização da GFP | K91: S4 | L91: AGJ | M91: 2 | O91: Backlog
A92: HIIP | B92: PFM | C92: Diagnóstico apresentado ao TWG-PFM; posição registada; ata com decisões; alterações incorporadas em versão datada | D92: 46444 | E92: Não iniciada | F92: Alinhamento com parceiros | G92: Divisão de trabalho documentada com o UNDP e o Banco Mundial | H92: 46346 | I92: Não iniciado | J92: Documentar a divisão de trabalho entre as três instituições | K92: S8 | L92: AGJ | M92: 1 | N92: Alinhamento | O92: Backlog
A93: HIIP | B93: PFM | C93: Diagnóstico apresentado ao TWG-PFM; posição registada; ata com decisões; alterações incorporadas em versão datada | D93: 46444 | E93: Não iniciada | J93: Apresentar o diagnóstico ao TWG-PFM para validação | K93: S14 | L93: AGJ | M93: 1 | N93: Relatório final | O93: Backlog
A94: HIIP | B94: Investment case - PHC | C94: Duas validações: diálogo no MINSA com a Ministra sobre a v1 (06/11/2026); validação técnica da v2, com HHFA, pelo TWG-PHC (26/02/2027) | D94: 46444 | E94: Não iniciada | F94: Estrutura e estratégia de materialização | G94: Estrutura do documento acordada internamente; atores-chave identificados por posição e influência; sequência de conversas planeada até novembro | H94: 46304 | I94: Não iniciado | J94: Definir a estrutura do investment case | K94: S5 | L94: AGJ | M94: 2 | O94: Backlog
A95: HIIP | B95: Investment case - PHC | C95: Duas validações: diálogo no MINSA com a Ministra sobre a v1 (06/11/2026); validação técnica da v2, com HHFA, pelo TWG-PHC (26/02/2027) | D95: 46444 | E95: Não iniciada | F95: Estrutura e estratégia de materialização | G95: Estrutura do documento acordada internamente; atores-chave identificados por posição e influência; sequência de conversas planeada até novembro | H95: 46304 | I95: Não iniciado | J95: Identificar os atores cujo apoio dá poder ao documento dentro do MINSA | K95: S5 | L95: AGJ | M95: 2 | O95: Backlog
A96: HIIP | B96: Investment case - PHC | C96: Duas validações: diálogo no MINSA com a Ministra sobre a v1 (06/11/2026); validação técnica da v2, com HHFA, pelo TWG-PHC (26/02/2027) | D96: 46444 | E96: Não iniciada | F96: Estrutura e estratégia de materialização | G96: Estrutura do documento acordada internamente; atores-chave identificados por posição e influência; sequência de conversas planeada até novembro | H96: 46304 | I96: Não iniciado | J96: Planear o engajamento desses atores ao longo da produção | K96: S5 | L96: AGJ | M96: 2 | N96: Atores identificados | O96: Backlog
A97: HIIP | B97: Investment case - PHC | C97: Duas validações: diálogo no MINSA com a Ministra sobre a v1 (06/11/2026); validação técnica da v2, com HHFA, pelo TWG-PHC (26/02/2027) | D97: 46444 | E97: Não iniciada | F97: Base de evidência financeira | G97: Dados de financiamento reunidos com fonte e data de extração; mapeamento de doadores obtido do project scoping; lacuna de financiamento estimada em ordem de grandeza | H97: 46318 | I97: Não iniciado | J97: Reunir os dados de financiamento disponíveis | K97: S6 | L97: AGJ | M97: 3 | O97: Backlog
A98: HIIP | B98: Investment case - PHC | C98: Duas validações: diálogo no MINSA com a Ministra sobre a v1 (06/11/2026); validação técnica da v2, com HHFA, pelo TWG-PHC (26/02/2027) | D98: 46444 | E98: Não iniciada | F98: Base de evidência financeira | G98: Dados de financiamento reunidos com fonte e data de extração; mapeamento de doadores obtido do project scoping; lacuna de financiamento estimada em ordem de grandeza | H98: 46318 | I98: Não iniciado | J98: Obter do project scoping o mapeamento de projetos e doadores | K98: S6 | L98: AGJ | M98: 1 | N98: Mapeamento de doadores | O98: Backlog
A99: HIIP | B99: Investment case - PHC | C99: Duas validações: diálogo no MINSA com a Ministra sobre a v1 (06/11/2026); validação técnica da v2, com HHFA, pelo TWG-PHC (26/02/2027) | D99: 46444 | E99: Não iniciada | F99: Base de evidência financeira | G99: Dados de financiamento reunidos com fonte e data de extração; mapeamento de doadores obtido do project scoping; lacuna de financiamento estimada em ordem de grandeza | H99: 46318 | I99: Não iniciado | J99: Estimar a lacuna de financiamento dos CSP em ordem de grandeza | K99: S6 | L99: AGJ | M99: 3 | N99: Dados de financiamento | O99: Backlog
A100: HIIP | B100: Investment case - PHC | C100: Duas validações: diálogo no MINSA com a Ministra sobre a v1 (06/11/2026); validação técnica da v2, com HHFA, pelo TWG-PHC (26/02/2027) | D100: 46444 | E100: Não iniciada | F100: Investment case v1 | G100: Narrativa por área priorizada escrita; revisão do country office resolvida; versão datada e pronta para o diálogo com a Ministra | H100: 46332 | I100: Não iniciado | J100: Escrever a narrativa de investimento por área priorizada | K100: S6 | L100: AGJ | M100: 4 | N100: Estratégia v1; base de evidência | O100: Backlog
A101: HIIP | B101: Investment case - PHC | C101: Duas validações: diálogo no MINSA com a Ministra sobre a v1 (06/11/2026); validação técnica da v2, com HHFA, pelo TWG-PHC (26/02/2027) | D101: 46444 | E101: Não iniciada | F101: Investment case v1 | G101: Narrativa por área priorizada escrita; revisão do country office resolvida; versão datada e pronta para o diálogo com a Ministra | H101: 46332 | I101: Não iniciado | J101: Redigir o investment case v1 | K101: S7 | L101: AGJ | M101: 5 | N101: Narrativa de investimento | O101: Backlog
A102: HIIP | B102: Investment case - PHC | C102: Duas validações: diálogo no MINSA com a Ministra sobre a v1 (06/11/2026); validação técnica da v2, com HHFA, pelo TWG-PHC (26/02/2027) | D102: 46444 | E102: Não iniciada | F102: Investment case v1 | G102: Narrativa por área priorizada escrita; revisão do country office resolvida; versão datada e pronta para o diálogo com a Ministra | H102: 46332 | I102: Não iniciado | J102: Revisão do country office | K102: S7 | L102: AGJ | M102: 2 | N102: Investment case v1 | O102: Backlog
A103: HIIP | B103: Investment case - PHC | C103: Duas validações: diálogo no MINSA com a Ministra sobre a v1 (06/11/2026); validação técnica da v2, com HHFA, pelo TWG-PHC (26/02/2027) | D103: 46444 | E103: Não iniciada | F103: Investment case v2 com HHFA | G103: Achados do HHFA incorporados; números revistos; versão datada | H103: 46444 | I103: Não iniciado | J103: Incorporar os achados do HHFA | K103: S14 | L103: AGJ | M103: 4 | N103: Relatório do HHFA | O103: Backlog
A104: HIIP | B104: Investment case - PHC | C104: Duas validações: diálogo no MINSA com a Ministra sobre a v1 (06/11/2026); validação técnica da v2, com HHFA, pelo TWG-PHC (26/02/2027) | D104: 46444 | E104: Não iniciada | F104: Investment case v2 com HHFA | G104: Achados do HHFA incorporados; números revistos; versão datada | H104: 46444 | I104: Não iniciado | J104: Rever os números e a narrativa | K104: S14 | L104: AGJ | M104: 2 | N104: Achados do HHFA incorporados | O104: Backlog
...

Sheet 3. Tarefas
A1: Backlog de tarefas, ordenado por sprint
A3: Sprint | B3: Frente | C3: Resultado | D3: Tarefa | E3: Responsável | F3: Estimativa (dias) | G3: Depende de | H3: Estado | I3: Aprendizado
A4: S1 | B4: Background document - PHC | C4: Auditoria do trabalho anterior das consultoras | D4: Reuniões com as consultoras | E4: AGJ | F4: 2 | H4: Done
A5: S1 | B5: Background document - PHC | C5: Auditoria do trabalho anterior das consultoras | D5: Identificação da metodologia previamente aplicada | E5: AGJ | F5: 2 | H5: Done
A6: S1 | B6: PFM | C6: TWG-PFM constituído | D6: Finalizar o ToR do TWG-PFM | E6: AGJ | F6: 2 | H6: Done
A7: S2 | B7: Background document - PHC | C7: Auditoria do trabalho anterior das consultoras | D7: Inventário dos dados recolhidos e dos que faltam recolher | E7: AGJ | F7: 2 | H7: Done
A8: S2 | B8: Background document - PHC | C8: Auditoria do trabalho anterior das consultoras | D8: Levantamento do que foi prometido ao cliente, com prazos e produtos | E8: AGJ | F8: 2 | H8: Done
A9: S2 | B9: PFM | C9: TWG-PFM constituído | D9: Confirmar a lista de participantes | E9: AGJ | F9: 2 | G9: ToR | H9: Done
A10: S3 | B10: Background document - PHC | C10: Estrutura analítica | D10: Estruturar o documento pelas alavancas do operational framework | E10: AGJ | F10: 2 | G10: Auditoria | H10: Backlog
A11: S3 | B11: Background document - PHC | C11: Estrutura analítica | D11: Reescrever os guias de entrevista mapeados nas alavancas | E11: AGJ | F11: 3 | G11: Estrutura analítica | H11: Backlog
A12: S3 | B12: Background document - PHC | C12: Estrutura analítica | D12: Mapear o material das consultoras contra as alavancas | E12: AGJ | F12: 2 | G12: Estrutura analítica | H12: Backlog
A13: S3 | B13: Background document - PHC | C13: Estrutura analítica | D13: Definir a forma de apresentação de barreiras, lacunas, gargalos e fortalezas | E13: AGJ | F13: 1 | H13: Backlog
A14: S3 | B14: Background document - PHC | C14: Espinha dorsal quantitativa | D14: Extrair os indicadores do DHIS2 | E14: AGJ | F14: 3 | H14: Backlog
A15: S3 | B15: Background document - PHC | C15: Espinha dorsal quantitativa | D15: Avaliar a qualidade e a completude dos dados extraídos | E15: AGJ | F15: 2 | G15: Extração do DHIS2 | H15: Backlog
A16: S3 | B16: Background document - PHC | C16: Espinha dorsal quantitativa | D16: Identificar anomalias a interrogar no campo | E16: AGJ | F16: 1 | G16: Avaliação de qualidade | H16: Backlog
A17: S3 | B17: Background document - PHC | C17: Preparação das visitas piloto | D17: Pedir anuência à DNSP para as visitas e entrevistas piloto | E17: AGJ | F17: 2 | H17: Backlog
A18: S3 | B18: Background document - PHC | C18: Preparação das visitas piloto | D18: Selecionar do HHFA o que capturar neste piloto | E18: AGJ | F18: 2 | H18: Backlog
A19: S3 | B19: Background document - PHC | C19: Preparação das visitas piloto | D19: Preparar os questionários a partir do HHFA | E19: AGJ | F19: 3 | G19: Seleção de itens do HHFA | H19: Backlog
A20: S3 | B20: Background document - PHC | C20: Preparação das visitas piloto | D20: Carregar os questionários no KoboToolbox | E20: AGJ | F20: 1 | G20: Questionários preparados | H20: Backlog
A21: S3 | B21: Background document - PHC | C21: Preparação das visitas piloto | D21: Definir unidades, datas e perfis de informantes | E21: AGJ | F21: 2 | G21: Anuência da DNSP | H21: Backlog
A22: S3 | B22: HHFA e diagnóstico situacional | C22: Acordo interagências | D22: Manter as reuniões de alinhamento com o UNICEF e o UNFPA | E22: AGJ | F22: 2 | H22: In progress
A23: S3 | B23: HHFA e diagnóstico situacional | C23: Adesão ao inquérito já contratado | D23: Obter e rever a amostragem, o ToR e o contrato já decididos | E23: AGJ | F23: 1 | H23: Backlog
A24: S3 | B24: HHFA e diagnóstico situacional | C24: Adesão ao inquérito já contratado | D24: Avaliar se a amostra serve às perguntas do diagnóstico dos CSP | E24: AGJ | F24: 2 | G24: Amostragem obtida | H24: Backlog
A25: S3 | B25: HHFA e diagnóstico situacional | C25: Adesão ao inquérito já contratado | D25: Identificar que margem existe para acrescentar itens ao instrumento | E25: AGJ | F25: 1 | G25: Avaliação da amostra | H25: Backlog
A26: S3 | B26: HHFA e diagnóstico situacional | C26: Adesão ao inquérito já contratado | D26: Participar na reunião de arranque com a empresa contratada | E26: AGJ | F26: 1 | H26: Backlog
A27: S3 | B27: HHFA e diagnóstico situacional | C27: Adesão ao inquérito já contratado | D27: Alinhar o cronograma de recolha com o calendário do HIIP | E27: AGJ | F27: 1 | G27: Reunião de arranque | H27: Backlog
A28: S3 | B28: HHFA e diagnóstico situacional | C28: Seleção de itens | D28: Selecionar do HHFA os itens a capturar no piloto | E28: AGJ | F28: 2 | G28: Margem de inclusão confirmada | H28: Backlog
A29: S3 | B29: PFM | C29: TWG-PFM constituído | D29: Organizar o cronograma e enviar os convites | E29: AGJ | F29: 2 | G29: Lista de participantes | H29: In progress
A30: S3 | B30: PFM | C30: TWG-PFM constituído | D30: Conduzir as entrevistas preparatórias com os membros | E30: AGJ | F30: 4 | G30: Convites | H30: Backlog
A31: S3 | B31: PFM | C31: Consultoria PFM contratada | D31: Reunião com o Banco Mundial sobre o financiamento do especialista local | E31: AGJ | F31: 1 | H31: Backlog
A32: S3 | B32: Relatórios contratuais do HIIP | C32: Calendário de reporte | D32: Confirmar o calendário contratual de reporte | E32: AGJ | F32: 1 | H32: Backlog
A33: S3 | B33: TWG-PHC | C33: Proposta de reconstituição do TWG-PHC | D33: Identificar os atores anteriormente convocados | E33: AGJ | F33: 2 | H33: Backlog
A34: S3 | B34: TWG-PHC | C34: Proposta de reconstituição do TWG-PHC | D34: Identificar que atores faltam convocar | E34: AGJ | F34: 1 | G34: Atores anteriores identificados | H34: Backlog
A35: S4 | B35: Background document - PHC | C35: Visitas piloto realizadas | D35: Conduzir as visitas às unidades sanitárias | E35: AGJ | F35: 6 | G35: Preparação das visitas piloto | H35: Backlog
A36: S4 | B36: Background document - PHC | C36: Visitas piloto realizadas | D36: Conduzir entrevistas com profissionais e gestores locais, provinciais e nacionais | E36: AGJ | F36: 4 | G36: Preparação das visitas piloto | H36: Backlog
A37: S4 | B37: Background document - PHC | C37: Visitas piloto realizadas | D37: Registar e organizar o material recolhido | E37: AGJ | F37: 2 | G37: Visitas realizadas | H37: Backlog
A38: S4 | B38: Background document - PHC | C38: Visitas piloto realizadas | D38: Registar as lições do piloto para o desenho do HHFA | E38: AGJ | F38: 1 | G38: Visitas realizadas | H38: Backlog
A39: S4 | B39: HHFA e diagnóstico situacional | C39: Acordo interagências | D39: Definir o âmbito partilhado e a divisão de custos | E39: AGJ | F39: 2 | G39: Reuniões de alinhamento | H39: Backlog
A40: S4 | B40: PFM | C40: TWG-PFM constituído | D40: Produzir o relatório das entrevistas preparatórias | E40: AGJ | F40: 3 | G40: Entrevistas preparatórias | H40: Backlog
A41: S4 | B41: PFM | C41: TWG-PFM constituído | D41: Conduzir a sessão inaugural | E41: AGJ | F41: 1 | G41: Relatório das entrevistas | H41: Backlog
A42: S4 | B42: PFM | C42: TWG-PFM constituído | D42: Acordar o plano de trabalho e o calendário quinzenal | E42: AGJ | F42: 1 | G42: Sessão inaugural | H42: Backlog
A43: S4 | B43: PFM | C43: Consultoria PFM contratada | D43: Redigir o ToR e as especificações da consultoria | E43: AGJ | F43: 3 | G43: Relatório das entrevistas | H43: Backlog
A44: S4 | B44: PFM | C44: Alinhamento com parceiros | D44: Alinhar com o UNDP e o Banco Mundial sobre as frentes de modernização da GFP | E44: AGJ | F44: 2 | H44: Backlog
A45: S4 | B45: TWG-PHC | C45: Proposta de reconstituição do TWG-PHC | D45: Planear as atividades do grupo de trabalho | E45: AGJ | F45: 3 | G45: Lista de atores | H45: Backlog
A46: S5 | B46: Background document - PHC | C46: Síntese e mapeamento | D46: Codificar e sintetizar os achados qualitativos | E46: AGJ | F46: 4 | G46: Visitas piloto realizadas | H46: Backlog
A47: S5 | B47: Background document - PHC | C47: Síntese e mapeamento | D47: Mapear barreiras, lacunas, gargalos e fortalezas por estrutura, processo e resultado | E47: AGJ | F47: 3 | G47: Síntese qualitativa | H47: Backlog
A48: S5 | B48: Background document - PHC | C48: Síntese e mapeamento | D48: Descrever o modelo de cuidados atual | E48: AGJ | F48: 3 | G48: Síntese qualitativa | H48: Backlog
A49: S5 | B49: Background document - PHC | C49: Síntese e mapeamento | D49: Contrapor as evidências dos informantes à evidência científica atual | E49: AGJ | F49: 3 | G49: Mapeamento | H49: Backlog
A50: S5 | B50: Background document - PHC | C50: Background document v1 | D50: Redigir a secção de contraste entre o que se acredita e o que se observou | E50: AGJ | F50: 2 | G50: Síntese e mapeamento | H50: Backlog
A51: S5 | B51: Background document - PHC | C51: Background document v1 | D51: Redigir o background document v1 | E51: AGJ | F51: 5 | G51: Síntese e mapeamento | H51: Backlog
A52: S5 | B52: HHFA e diagnóstico situacional | C52: Acordo interagências | D52: Formalizar o acordo de cofinanciamento | E52: AGJ | F52: 2 | G52: Âmbito e custos definidos | H52: Backlog
A53: S5 | B53: HHFA e diagnóstico situacional | C53: Seleção de itens | D53: Definir a lista de itens sumários a partir do piloto | E53: AGJ | F53: 3 | G53: Visitas piloto realizadas | H53: Backlog
A54: S5 | B54: Investment case - PHC | C54: Estrutura e estratégia de materialização | D54: Definir a estrutura do investment case | E54: AGJ | F54: 2 | H54: Backlog
A55: S5 | B55: Investment case - PHC | C55: Estrutura e estratégia de materialização | D55: Identificar os atores cujo apoio dá poder ao documento dentro do MINSA | E55: AGJ | F55: 2 | H55: Backlog
A56: S5 | B56: Investment case - PHC | C56: Estrutura e estratégia de materialização | D56: Planear o engajamento desses atores ao longo da produção | E56: AGJ | F56: 2 | G56: Atores identificados | H56: Backlog
A57: S5 | B57: PFM | C57: Consultoria PFM contratada | D57: Conduzir o processo de seleção | E57: AGJ | F57: 5 | G57: ToR da consultoria | H57: Backlog
A58: S5 | B58: Strategy document - PHC | C58: Mapa de barreiras, lacunas, gargalos e fortalezas | D58: Mapear barreiras, lacunas, gargalos e fortalezas por estrutura, processo e resultado | E58: AGJ | F58: 4 | G58: Síntese qualitativa do campo | H58: Backlog
A59: S5 | B59: Strategy document - PHC | C59: Mapa de barreiras, lacunas, gargalos e fortalezas | D59: Rever evidência de intervenções para cada barreira, lacuna e gargalo | E59: AGJ | F59: 5 | G59: Mapa de barreiras | H59: Backlog
A60: S5 | B60: Strategy document - PHC | C60: Teoria da mudança e leque de opções | D60: Desenhar a teoria da mudança | E60: AGJ | F60: 3 | G60: Tabela de evidência | H60: Backlog
A61: S5 | B61: Strategy document - PHC | C61: Teoria da mudança e leque de opções | D61: Construir o leque de opções para debate | E61: AGJ | F61: 3 | G61: Teoria da mudança | H61: Backlog
A62: S5 | B62: Strategy document - PHC | C62: Teoria da mudança e leque de opções | D62: Identificação de áreas e ações para priorização | E62: AGJ | F62: 3 | G62: Leque de opções | H62: Backlog
A63: S5 | B63: Strategy document - PHC | C63: Estratégia v1 com áreas priorizadas | D63: Redigir a estratégia v1 | E63: AGJ | F63: 5 | G63: Áreas e ações priorizadas | H63: Backlog
A64: S5 | B64: TWG-PHC | C64: Proposta de reconstituição do TWG-PHC | D64: Preparar o pedido de autorização às autoridades | E64: AGJ | F64: 1 | G64: Plano de atividades | H64: Backlog
A65: S5 | B65: TWG-PHC | D65: Obter autorização formal das autoridades | E65: AGJ | F65: 2 | G65: Pedido de autorização; anuência da DNSP | H65: Backlog
A66: S6 | B66: Background document - PHC | C66: Background document v1 | D66: Adequar a linguagem ao cliente | E66: AGJ | F66: 2 | G66: Background document v1 | H66: Backlog
A67: S6 | B67: Background document - PHC | C67: Background document v1 | D67: Rever evidências e referências | E67: AGJ | F67: 2 | G67: Background document v1 | H67: Backlog
A68: S6 | B68: Background document - PHC | C68: Background document v1 | D68: Revisão do country office | E68: AGJ | F68: 2 | G68: Background document v1 | H68: Backlog
A69: S6 | B69: Background document - PHC | D69: Apresentar o documento ao TWG-PHC para validação | E69: AGJ | F69: 1 | G69: TWG-PHC refundado; Background v1 | H69: Backlog
A70: S6 | B70: HHFA e diagnóstico situacional | C70: Instrumento | D70: Adaptar o instrumento HHFA ao contexto angolano | E70: AGJ | F70: 4 | G70: Lista de itens sumários | H70: Backlog
A71: S6 | B71: HHFA e diagnóstico situacional | C71: Instrumento | D71: Programar o instrumento no KoboToolbox | E71: AGJ | F71: 2 | G71: Instrumento adaptado | H71: Backlog
A72: S6 | B72: HHFA e diagnóstico situacional | C72: Instrumento | D72: Pré-testar o instrumento | E72: AGJ | F72: 1 | G72: Instrumento programado | H72: Backlog
A73: S6 | B73: HHFA e diagnóstico situacional | C73: Instrumento | D73: Documentar o desenho de métodos mistos sequencial exploratório | E73: AGJ | F73: 2 | H73: Backlog
A74: S6 | B74: Investment case - PHC | C74: Base de evidência financeira | D74: Reunir os dados de financiamento disponíveis | E74: AGJ | F74: 3 | H74: Backlog
A75: S6 | B75: Investment case - PHC | C75: Base de evidência financeira | D75: Obter do project scoping o mapeamento de projetos e doadores | E75: AGJ | F75: 1 | G75: Mapeamento de doadores | H75: Backlog
A76: S6 | B76: Investment case - PHC | C76: Base de evidência financeira | D76: Estimar a lacuna de financiamento dos CSP em ordem de grandeza | E76: AGJ | F76: 3 | G76: Dados de financiamento | H76: Backlog
A77: S6 | B77: Investment case - PHC | C77: Investment case v1 | D77: Escrever a narrativa de investimento por área priorizada | E77: AGJ | F77: 4 | G77: Estratégia v1; base de evidência | H77: Backlog
A78: S6 | B78: Modelo de cuidados e perfis profissionais - PHC | C78: Diagnóstico do modelo atual | D78: Descrever o modelo de cuidados vigente nos CSP | E78: AGJ | F78: 3 | G78: Síntese qualitativa do campo | H78: Backlog
A79: S6 | B79: Modelo de cuidados e perfis profissionais - PHC | C79: Diagnóstico do modelo atual | D79: Identificar as limitações do modelo atual | E79: AGJ | F79: 2 | G79: Modelo vigente descrito | H79: Backlog
A80: S6 | B80: Modelo de cuidados e perfis profissionais - PHC | C80: Diagnóstico do modelo atual | D80: Mapear a composição atual das equipas e as funções efetivamente exercidas | E80: AGJ | F80: 3 | G80: Visitas piloto | H80: Backlog
A81: S6 | B81: PFM | C81: Consultoria PFM contratada | D81: Contratar a consultoria | E81: AGJ | F81: 2 | G81: Processo de seleção | H81: Backlog
A82: S6 | B82: PFM | C82: Consultoria PFM contratada | D82: Integrar o especialista local | E82: AGJ | F82: 3 | G82: Acordo com o Banco Mundial | H82: Backlog
A83: S6 | B83: Project scoping - PHC | C83: Mapeamento de projetos e doadores | D83: Mapear os projetos que financiam CSP atualmente | E83: AGJ | F83: 3 | H83: Backlog
A84: S6 | B84: Project scoping - PHC | C84: Mapeamento de projetos e doadores | D84: Identificar quem financia o quê, para quê e onde | E84: AGJ | F84: 3 | G84: Projetos mapeados | H84: Backlog
A85: S6 | B85: Project scoping - PHC | C85: Mapeamento de projetos e doadores | D85: Identificar sobreposições e lacunas geográficas e temáticas | E85: AGJ | F85: 2 | G85: Mapeamento | H85: Backlog
A86: S6 | B86: Strategy document - PHC | C86: Estratégia v1 com áreas priorizadas | D86: Revisão interna e pré-alinhamento com o MINSA | E86: AGJ | F86: 2 | G86: Estratégia v1 | H86: Backlog
A87: S6 | B87: TWG-PHC | D87: Convidar as autoridades e os membros | E87: AGJ | F87: 1 | G87: Autorização formal | H87: Backlog
A88: S6 | B88: TWG-PHC | D88: Agendar o encontro com todos | E88: AGJ | F88: 1 | G88: Convites enviados | H88: Backlog
A89: S6 | B89: TWG-PHC | D89: Conduzir a sessão de refundação do grupo | E89: AGJ | F89: 1 | G89: Encontro agendado | H89: Backlog
A90: S7 | B90: Background document - PHC | D90: Incorporar os comentários do TWG-PHC | E90: AGJ | F90: 2 | G90: Sessão de validação | H90: Backlog
A91: S7 | B91: HHFA e diagnóstico situacional | C91: Recolha | D91: Acompanhar a formação dos inquiridores da empresa | E91: AGJ | F91: 2 | G91: Instrumento pré-testado | H91: Backlog
A92: S7 | B92: HHFA e diagnóstico situacional | C92: Recolha | D92: Acompanhar a logística de terreno | E92: AGJ | F92: 1 | H92: Backlog
A93: S7 | B93: Investment case - PHC | C93: Investment case v1 | D93: Redigir o investment case v1 | E93: AGJ | F93: 5 | G93: Narrativa de investimento | H93: Backlog
A94: S7 | B94: Investment case - PHC | C94: Investment case v1 | D94: Revisão do country office | E94: AGJ | F94: 2 | G94: Investment case v1 | H94: Backlog
A95: S7 | B95: Investment case - PHC | D95: Apresentar a v1 no diálogo interno do MINSA, com a Ministra | E95: AGJ | F95: 1 | G95: Investment case v1 | H95: Backlog
A96: S7 | B96: PFM | C96: Consultoria PFM contratada | D96: Reunião de arranque e validação do plano de trabalho | E96: AGJ | F96: 2 | G96: Contrato assinado | H96: Backlog
A97: S7 | B97: Strategy document - PHC | D97: Conduzir o policy dialogue de validação | E97: AGJ | F97: 2 | G97: TWG-PHC refundado; Estratégia v1 | H97: Backlog
A98: S8 | B98: Essential package - PHC | C98: Critérios e âmbito | D98: Definir os critérios de inclusão de serviços no pacote | E98: AGJ | F98: 3 | G98: Estratégia validada | H98: Backlog
A99: S8 | B99: Essential package - PHC | C99: Critérios e âmbito | D99: Delimitar o âmbito por nível de unidade sanitária | E99: AGJ | F99: 2 | G99: Critérios de inclusão | H99: Backlog
A100: S8 | B100: Modelo de cuidados e perfis profissionais - PHC | C100: Novo modelo de cuidados | D100: Definir os princípios do novo modelo | E100: AGJ | F100: 2 | G100: Diagnóstico do modelo atual | H100: Backlog
A101: S8 | B101: Modelo de cuidados e perfis profissionais - PHC | C101: Novo modelo de cuidados | D101: Desenhar o modelo proposto | E101: AGJ | F101: 5 | G101: Princípios definidos | H101: Backlog
...

Sheet 4. Sprints
A1: Calendário de sprints - quinzenal, 3 de agosto de 2026 a 2 de julho de 2027
A3: Sprint | B3: Início | C3: Fim | D3: Tarefas previstas | E3: Dias previstos
A4: S1 | B4: 46237 | C4: 46248 | D4: =COUNTIF('3. Tarefas'!$A$4:$A$162,$A4) -> 3 | E4: =SUMIF('3. Tarefas'!$A$4:$A$162,$A4,'3. Tarefas'!$F$4:$F$162) -> 6
A5: S2 | B5: 46251 | C5: 46262 | D5: =COUNTIF('3. Tarefas'!$A$4:$A$162,$A5) -> 3 | E5: =SUMIF('3. Tarefas'!$A$4:$A$162,$A5,'3. Tarefas'!$F$4:$F$162) -> 6
A6: S3 | B6: 46265 | C6: 46276 | D6: =COUNTIF('3. Tarefas'!$A$4:$A$162,$A6) -> 25 | E6: =SUMIF('3. Tarefas'!$A$4:$A$162,$A6,'3. Tarefas'!$F$4:$F$162) -> 45
A7: S4 | B7: 46279 | C7: 46290 | D7: =COUNTIF('3. Tarefas'!$A$4:$A$162,$A7) -> 11 | E7: =SUMIF('3. Tarefas'!$A$4:$A$162,$A7,'3. Tarefas'!$F$4:$F$162) -> 28
A8: S5 | B8: 46293 | C8: 46304 | D8: =COUNTIF('3. Tarefas'!$A$4:$A$162,$A8) -> 20 | E8: =SUMIF('3. Tarefas'!$A$4:$A$162,$A8,'3. Tarefas'!$F$4:$F$162) -> 62
A9: S6 | B9: 46307 | C9: 46318 | D9: =COUNTIF('3. Tarefas'!$A$4:$A$162,$A9) -> 24 | E9: =SUMIF('3. Tarefas'!$A$4:$A$162,$A9,'3. Tarefas'!$F$4:$F$162) -> 53
A10: S7 | B10: 46321 | C10: 46332 | D10: =COUNTIF('3. Tarefas'!$A$4:$A$162,$A10) -> 8 | E10: =SUMIF('3. Tarefas'!$A$4:$A$162,$A10,'3. Tarefas'!$F$4:$F$162) -> 17
A11: S8 | B11: 46335 | C11: 46346 | D11: =COUNTIF('3. Tarefas'!$A$4:$A$162,$A11) -> 12 | E11: =SUMIF('3. Tarefas'!$A$4:$A$162,$A11,'3. Tarefas'!$F$4:$F$162) -> 34
A12: S9 | B12: 46349 | C12: 46360 | D12: =COUNTIF('3. Tarefas'!$A$4:$A$162,$A12) -> 9 | E12: =SUMIF('3. Tarefas'!$A$4:$A$162,$A12,'3. Tarefas'!$F$4:$F$162) -> 27
A13: S10 | B13: 46363 | C13: 46374 | D13: =COUNTIF('3. Tarefas'!$A$4:$A$162,$A13) -> 6 | E13: =SUMIF('3. Tarefas'!$A$4:$A$162,$A13,'3. Tarefas'!$F$4:$F$162) -> 23
A14: S11 | B14: 46391 | C14: 46402 | D14: =COUNTIF('3. Tarefas'!$A$4:$A$162,$A14) -> 3 | E14: =SUMIF('3. Tarefas'!$A$4:$A$162,$A14,'3. Tarefas'!$F$4:$F$162) -> 12
A15: S12 | B15: 46405 | C15: 46416 | D15: =COUNTIF('3. Tarefas'!$A$4:$A$162,$A15) -> 3 | E15: =SUMIF('3. Tarefas'!$A$4:$A$162,$A15,'3. Tarefas'!$F$4:$F$162) -> 13
... A26: S23 | B26: 46559 | C26: 46570 | D26: =COUNTIF('3. Tarefas'!$A$4:$A$162,$A26) -> 0 | E26: =SUMIF('3. Tarefas'!$A$4:$A$162,$A26,'3. Tarefas'!$F$4:$F$162) -> 0
A27: Recorrente | D27: =COUNTIF('3. Tarefas'!$A$4:$A$162,"Recorrente") -> 4 | E27: =SUMIF('3. Tarefas'!$A$4:$A$162,"Recorrente",'3. Tarefas'!$F$4:$F$162) -> 6
A28: TBC | D28: =COUNTIF('3. Tarefas'!$A$4:$A$162,"TBC") -> 4 | E28: =SUMIF('3. Tarefas'!$A$4:$A$162,"TBC",'3. Tarefas'!$F$4:$F$162) -> 16

Sheet 1. TWG-PHC
A1: TWG-PHC
A3: Projeto | B3: Frente de trabalho (produto) | C3: Validação externa | D3: Data validação | E3: Estado validação | F3: Resultado (output) | G3: Definição de feito (resultado) | H3: Data resultado | I3: Estado resultado | J3: Tarefa | K3: Sprint | L3: Responsável | M3: Estimativa (dias) | N3: Depende de | O3: Estado tarefa | P3: Aprendizado
A4: HIIP | B4: TWG-PHC | C4: Autoridades autorizam formalmente a reconstituição do grupo; sessão de refundação realizada com quórum; plano de atividades aceite pelos membros | D4: 46318 | E4: Não iniciada | F4: Proposta de reconstituição do TWG-PHC | G4: Lista de atores anteriores identificada; lacunas de representação identificadas; plano de atividades redigido; convites e pedido de autorização preparados | H4: 46304 | I4: Não iniciado | J4: Identificar os atores anteriormente convocados | K4: S3 | L4: AGJ | M4: 2 | O4: Backlog
A5: HIIP | B5: TWG-PHC | C5: Autoridades autorizam formalmente a reconstituição do grupo; sessão de refundação realizada com quórum; plano de atividades aceite pelos membros | D5: 46318 | E5: Não iniciada | F5: Proposta de reconstituição do TWG-PHC | G5: Lista de atores anteriores identificada; lacunas de representação identificadas; plano de atividades redigido; convites e pedido de autorização preparados | H5: 46304 | I5: Não iniciado | J5: Identificar que atores faltam convocar | K5: S3 | L5: AGJ | M5: 1 | N5: Atores anteriores identificados | O5: Backlog
A6: HIIP | B6: TWG-PHC | C6: Autoridades autorizam formalmente a reconstituição do grupo; sessão de refundação realizada com quórum; plano de atividades aceite pelos membros | D6: 46318 | E6: Não iniciada | F6: Proposta de reconstituição do TWG-PHC | G6: Lista de atores anteriores identificada; lacunas de representação identificadas; plano de atividades redigido; convites e pedido de autorização preparados | H6: 46304 | I6: Não iniciado | J6: Planear as atividades do grupo de trabalho | K6: S4 | L6: AGJ | M6: 3 | N6: Lista de atores | O6: Backlog
A7: HIIP | B7: TWG-PHC | C7: Autoridades autorizam formalmente a reconstituição do grupo; sessão de refundação realizada com quórum; plano de atividades aceite pelos membros | D7: 46318 | E7: Não iniciada | F7: Proposta de reconstituição do TWG-PHC | G7: Lista de atores anteriores identificada; lacunas de representação identificadas; plano de atividades redigido; convites e pedido de autorização preparados | H7: 46304 | I7: Não iniciado | J7: Preparar o pedido de autorização às autoridades | K7: S5 | L7: AGJ | M7: 1 | N7: Plano de atividades | O7: Backlog
A8: HIIP | B8: TWG-PHC | C8: Autoridades autorizam formalmente a reconstituição do grupo; sessão de refundação realizada com quórum; plano de atividades aceite pelos membros | D8: 46318 | E8: Não iniciada | J8: Obter autorização formal das autoridades | K8: S5 | L8: AGJ | M8: 2 | N8: Pedido de autorização; anuência da DNSP | O8: Backlog
A9: HIIP | B9: TWG-PHC | C9: Autoridades autorizam formalmente a reconstituição do grupo; sessão de refundação realizada com quórum; plano de atividades aceite pelos membros | D9: 46318 | E9: Não iniciada | J9: Convidar as autoridades e os membros | K9: S6 | L9: AGJ | M9: 1 | N9: Autorização formal | O9: Backlog
A10: HIIP | B10: TWG-PHC | C10: Autoridades autorizam formalmente a reconstituição do grupo; sessão de refundação realizada com quórum; plano de atividades aceite pelos membros | D10: 46318 | E10: Não iniciada | J10: Agendar o encontro com todos | K10: S6 | L10: AGJ | M10: 1 | N10: Convites enviados | O10: Backlog
A11: HIIP | B11: TWG-PHC | C11: Autoridades autorizam formalmente a reconstituição do grupo; sessão de refundação realizada com quórum; plano de atividades aceite pelos membros | D11: 46318 | E11: Não iniciada | J11: Conduzir a sessão de refundação do grupo | K11: S6 | L11: AGJ | M11: 1 | N11: Encontro agendado | O11: Backlog

Sheet 2. Background document
A1: Background document - PHC
A3: Projeto | B3: Frente de trabalho (produto) | C3: Validação externa | D3: Data validação | E3: Estado validação | F3: Resultado (output) | G3: Definição de feito (resultado) | H3: Data resultado | I3: Estado resultado | J3: Tarefa | K3: Sprint | L3: Responsável | M3: Estimativa (dias) | N3: Depende de | O3: Estado tarefa | P3: Aprendizado
A4: HIIP | B4: Background document - PHC | C4: Apresentado ao TWG-PHC; posição registada sobre o diagnóstico; ata com comentários e responsáveis; alterações incorporadas em versão datada | D4: 46332 | E4: Não iniciada | F4: Auditoria do trabalho anterior das consultoras | G4: Metodologia previamente aplicada identificada; inventário dos dados recolhidos e dos que faltam; registo do que foi prometido ao cliente, com prazos e produtos; lacunas listadas | H4: 46262 | I4: Feito | J4: Reuniões com as consultoras | K4: S1 | L4: AGJ | M4: 2 | O4: Done
A5: HIIP | B5: Background document - PHC | C5: Apresentado ao TWG-PHC; posição registada sobre o diagnóstico; ata com comentários e responsáveis; alterações incorporadas em versão datada | D5: 46332 | E5: Não iniciada | F5: Auditoria do trabalho anterior das consultoras | G5: Metodologia previamente aplicada identificada; inventário dos dados recolhidos e dos que faltam; registo do que foi prometido ao cliente, com prazos e produtos; lacunas listadas | H5: 46262 | I5: Feito | J5: Identificação da metodologia previamente aplicada | K5: S1 | L5: AGJ | M5: 2 | O5: Done
A6: HIIP | B6: Background document - PHC | C6: Apresentado ao TWG-PHC; posição registada sobre o diagnóstico; ata com comentários e responsáveis; alterações incorporadas em versão datada | D6: 46332 | E6: Não iniciada | F6: Auditoria do trabalho anterior das consultoras | G6: Metodologia previamente aplicada identificada; inventário dos dados recolhidos e dos que faltam; registo do que foi prometido ao cliente, com prazos e produtos; lacunas listadas | H6: 46262 | I6: Feito | J6: Inventário dos dados recolhidos e dos que faltam recolher | K6: S2 | L6: AGJ | M6: 2 | O6: Done
A7: HIIP | B7: Background document - PHC | C7: Apresentado ao TWG-PHC; posição registada sobre o diagnóstico; ata com comentários e responsáveis; alterações incorporadas em versão datada | D7: 46332 | E7: Não iniciada | F7: Auditoria do trabalho anterior das consultoras | G7: Metodologia previamente aplicada identificada; inventário dos dados recolhidos e dos que faltam; registo do que foi prometido ao cliente, com prazos e produtos; lacunas listadas | H7: 46262 | I7: Feito | J7: Levantamento do que foi prometido ao cliente, com prazos e produtos | K7: S2 | L7: AGJ | M7: 2 | O7: Done
A8: HIIP | B8: Background document - PHC | C8: Apresentado ao TWG-PHC; posição registada sobre o diagnóstico; ata com comentários e responsáveis; alterações incorporadas em versão datada | D8: 46332 | E8: Não iniciada | F8: Estrutura analítica | G8: Documento estruturado pelas alavancas do operational framework; guias de entrevista mapeados nas alavancas; material das consultoras mapeado; forma de apresentação de barreiras, lacunas, gargalos e fortalezas definida | H8: 46276 | I8: Não iniciado | J8: Estruturar o documento pelas alavancas do operational framework | K8: S3 | L8: AGJ | M8: 2 | N8: Auditoria | O8: Backlog
A9: HIIP | B9: Background document - PHC | C9: Apresentado ao TWG-PHC; posição registada sobre o diagnóstico; ata com comentários e responsáveis; alterações incorporadas em versão datada | D9: 46332 | E9: Não iniciada | F9: Estrutura analítica | G9: Documento estruturado pelas alavancas do operational framework; guias de entrevista mapeados nas alavancas; material das consultoras mapeado; forma de apresentação de barreiras, lacunas, gargalos e fortalezas definida | H9: 46276 | I9: Não iniciado | J9: Reescrever os guias de entrevista mapeados nas alavancas | K9: S3 | L9: AGJ | M9: 3 | N9: Estrutura analítica | O9: Backlog
A10: HIIP | B10: Background document - PHC | C10: Apresentado ao TWG-PHC; posição registada sobre o diagnóstico; ata com comentários e responsáveis; alterações incorporadas em versão datada | D10: 46332 | E10: Não iniciada | F10: Estrutura analítica | G10: Documento estruturado pelas alavancas do operational framework; guias de entrevista mapeados nas alavancas; material das consultoras mapeado; forma de apresentação de barreiras, lacunas, gargalos e fortalezas definida | H10: 46276 | I10: Não iniciado | J10: Mapear o material das consultoras contra as alavancas | K10: S3 | L10: AGJ | M10: 2 | N10: Estrutura analítica | O10: Backlog
A11: HIIP | B11: Background document - PHC | C11: Apresentado ao TWG-PHC; posição registada sobre o diagnóstico; ata com comentários e responsáveis; alterações incorporadas em versão datada | D11: 46332 | E11: Não iniciada | F11: Estrutura analítica | G11: Documento estruturado pelas alavancas do operational framework; guias de entrevista mapeados nas alavancas; material das consultoras mapeado; forma de apresentação de barreiras, lacunas, gargalos e fortalezas definida | H11: 46276 | I11: Não iniciado | J11: Definir a forma de apresentação de barreiras, lacunas, gargalos e fortalezas | K11: S3 | L11: AGJ | M11: 1 | O11: Backlog
A12: HIIP | B12: Background document - PHC | C12: Apresentado ao TWG-PHC; posição registada sobre o diagnóstico; ata com comentários e responsáveis; alterações incorporadas em versão datada | D12: 46332 | E12: Não iniciada | F12: Espinha dorsal quantitativa | G12: Indicadores extraídos com data de extração; qualidade e completude avaliadas; anomalias listadas para interrogar no campo | H12: 46276 | I12: Não iniciado | J12: Extrair os indicadores do DHIS2 | K12: S3 | L12: AGJ | M12: 3 | O12: Backlog
A13: HIIP | B13: Background document - PHC | C13: Apresentado ao TWG-PHC; posição registada sobre o diagnóstico; ata com comentários e responsáveis; alterações incorporadas em versão datada | D13: 46332 | E13: Não iniciada | F13: Espinha dorsal quantitativa | G13: Indicadores extraídos com data de extração; qualidade e completude avaliadas; anomalias listadas para interrogar no campo | H13: 46276 | I13: Não iniciado | J13: Avaliar a qualidade e a completude dos dados extraídos | K13: S3 | L13: AGJ | M13: 2 | N13: Extração do DHIS2 | O13: Backlog
A14: HIIP | B14: Background document - PHC | C14: Apresentado ao TWG-PHC; posição registada sobre o diagnóstico; ata com comentários e responsáveis; alterações incorporadas em versão datada | D14: 46332 | E14: Não iniciada | F14: Espinha dorsal quantitativa | G14: Indicadores extraídos com data de extração; qualidade e completude avaliadas; anomalias listadas para interrogar no campo | H14: 46276 | I14: Não iniciado | J14: Identificar anomalias a interrogar no campo | K14: S3 | L14: AGJ | M14: 1 | N14: Avaliação de qualidade | O14: Backlog
A15: HIIP | B15: Background document - PHC | C15: Apresentado ao TWG-PHC; posição registada sobre o diagnóstico; ata com comentários e responsáveis; alterações incorporadas em versão datada | D15: 46332 | E15: Não iniciada | F15: Preparação das visitas piloto | G15: Anuência da DNSP registada; itens do HHFA selecionados com justificação; questionários testados no dispositivo antes da partida; lista de unidades e informantes acordada | H15: 46276 | I15: Não iniciado | J15: Pedir anuência à DNSP para as visitas e entrevistas piloto | K15: S3 | L15: AGJ | M15: 2 | O15: Backlog
A16: HIIP | B16: Background document - PHC | C16: Apresentado ao TWG-PHC; posição registada sobre o diagnóstico; ata com comentários e responsáveis; alterações incorporadas em versão datada | D16: 46332 | E16: Não iniciada | F16: Preparação das visitas piloto | G16: Anuência da DNSP registada; itens do HHFA selecionados com justificação; questionários testados no dispositivo antes da partida; lista de unidades e informantes acordada | H16: 46276 | I16: Não iniciado | J16: Selecionar do HHFA o que capturar neste piloto | K16: S3 | L16: AGJ | M16: 2 | O16: Backlog
A17: HIIP | B17: Background document - PHC | C17: Apresentado ao TWG-PHC; posição registada sobre o diagnóstico; ata com comentários e responsáveis; alterações incorporadas em versão datada | D17: 46332 | E17: Não iniciada | F17: Preparação das visitas piloto | G17: Anuência da DNSP registada; itens do HHFA selecionados com justificação; questionários testados no dispositivo antes da partida; lista de unidades e informantes acordada | H17: 46276 | I17: Não iniciado | J17: Preparar os questionários a partir do HHFA | K17: S3 | L17: AGJ | M17: 3 | N17: Seleção de itens do HHFA | O17: Backlog
A18: HIIP | B18: Background document - PHC | C18: Apresentado ao TWG-PHC; posição registada sobre o diagnóstico; ata com comentários e responsáveis; alterações incorporadas em versão datada | D18: 46332 | E18: Não iniciada | F18: Preparação das visitas piloto | G18: Anuência da DNSP registada; itens do HHFA selecionados com justificação; questionários testados no dispositivo antes da partida; lista de unidades e informantes acordada | H18: 46276 | I18: Não iniciado | J18: Carregar os questionários no KoboToolbox | K18: S3 | L18: AGJ | M18: 1 | N18: Questionários preparados | O18: Backlog
A19: HIIP | B19: Background document - PHC | C19: Apresentado ao TWG-PHC; posição registada sobre o diagnóstico; ata com comentários e responsáveis; alterações incorporadas em versão datada | D19: 46332 | E19: Não iniciada | F19: Preparação das visitas piloto | G19: Anuência da DNSP registada; itens do HHFA selecionados com justificação; questionários testados no dispositivo antes da partida; lista de unidades e informantes acordada | H19: 46276 | I19: Não iniciado | J19: Definir unidades, datas e perfis de informantes | K19: S3 | L19: AGJ | M19: 2 | N19: Anuência da DNSP | O19: Backlog
A20: HIIP | B20: Background document - PHC | C20: Apresentado ao TWG-PHC; posição registada sobre o diagnóstico; ata com comentários e responsáveis; alterações incorporadas em versão datada | D20: 46332 | E20: Não iniciada | F20: Visitas piloto realizadas | G20: Unidades previstas visitadas; dados sincronizados do Kobo; notas de entrevista transcritas; limitações do instrumento anotadas | H20: 46290 | I20: Não iniciado | J20: Conduzir as visitas às unidades sanitárias | K20: S4 | L20: AGJ | M20: 6 | N20: Preparação das visitas piloto | O20: Backlog
A21: HIIP | B21: Background document - PHC | C21: Apresentado ao TWG-PHC; posição registada sobre o diagnóstico; ata com comentários e responsáveis; alterações incorporadas em versão datada | D21: 46332 | E21: Não iniciada | F21: Visitas piloto realizadas | G21: Unidades previstas visitadas; dados sincronizados do Kobo; notas de entrevista transcritas; limitações do instrumento anotadas | H21: 46290 | I21: Não iniciado | J21: Conduzir entrevistas com profissionais e gestores locais, provinciais e nacionais | K21: S4 | L21: AGJ | M21: 4 | N21: Preparação das visitas piloto | O21: Backlog
A22: HIIP | B22: Background document - PHC | C22: Apresentado ao TWG-PHC; posição registada sobre o diagnóstico; ata com comentários e responsáveis; alterações incorporadas em versão datada | D22: 46332 | E22: Não iniciada | F22: Visitas piloto realizadas | G22: Unidades previstas visitadas; dados sincronizados do Kobo; notas de entrevista transcritas; limitações do instrumento anotadas | H22: 46290 | I22: Não iniciado | J22: Registar e organizar o material recolhido | K22: S4 | L22: AGJ | M22: 2 | N22: Visitas realizadas | O22: Backlog
A23: HIIP | B23: Background document - PHC | C23: Apresentado ao TWG-PHC; posição registada sobre o diagnóstico; ata com comentários e responsáveis; alterações incorporadas em versão datada | D23: 46332 | E23: Não iniciada | F23: Visitas piloto realizadas | G23: Unidades previstas visitadas; dados sincronizados do Kobo; notas de entrevista transcritas; limitações do instrumento anotadas | H23: 46290 | I23: Não iniciado | J23: Registar as lições do piloto para o desenho do HHFA | K23: S4 | L23: AGJ | M23: 1 | N23: Visitas realizadas | O23: Backlog
A24: HIIP | B24: Background document - PHC | C24: Apresentado ao TWG-PHC; posição registada sobre o diagnóstico; ata com comentários e responsáveis; alterações incorporadas em versão datada | D24: 46332 | E24: Não iniciada | F24: Síntese e mapeamento | G24: Achados codificados; barreiras, lacunas, gargalos e fortalezas classificados por estrutura, processo e resultado e mapeados nas alavancas; modelo de cuidados atual descrito; evidências dos informantes contrapostas à evidência científica atual | H24: 46304 | I24: Não iniciado | J24: Codificar e sintetizar os achados qualitativos | K24: S5 | L24: AGJ | M24: 4 | N24: Visitas piloto realizadas | O24: Backlog
A25: HIIP | B25: Background document - PHC | C25: Apresentado ao TWG-PHC; posição registada sobre o diagnóstico; ata com comentários e responsáveis; alterações incorporadas em versão datada | D25: 46332 | E25: Não iniciada | F25: Síntese e mapeamento | G25: Achados codificados; barreiras, lacunas, gargalos e fortalezas classificados por estrutura, processo e resultado e mapeados nas alavancas; modelo de cuidados atual descrito; evidências dos informantes contrapostas à evidência científica atual | H25: 46304 | I25: Não iniciado | J25: Mapear barreiras, lacunas, gargalos e fortalezas por estrutura, processo e resultado | K25: S5 | L25: AGJ | M25: 3 | N25: Síntese qualitativa | O25: Backlog
A26: HIIP | B26: Background document - PHC | C26: Apresentado ao TWG-PHC; posição registada sobre o diagnóstico; ata com comentários e responsáveis; alterações incorporadas em versão datada | D26: 46332 | E26: Não iniciada | F26: Síntese e mapeamento | G26: Achados codificados; barreiras, lacunas, gargalos e fortalezas classificados por estrutura, processo e resultado e mapeados nas alavancas; modelo de cuidados atual descrito; evidências dos informantes contrapostas à evidência científica atual | H26: 46304 | I26: Não iniciado | J26: Descrever o modelo de cuidados atual | K26: S5 | L26: AGJ | M26: 3 | N26: Síntese qualitativa | O26: Backlog
A27: HIIP | B27: Background document - PHC | C27: Apresentado ao TWG-PHC; posição registada sobre o diagnóstico; ata com comentários e responsáveis; alterações incorporadas em versão datada | D27: 46332 | E27: Não iniciada | F27: Síntese e mapeamento | G27: Achados codificados; barreiras, lacunas, gargalos e fortalezas classificados por estrutura, processo e resultado e mapeados nas alavancas; modelo de cuidados atual descrito; evidências dos informantes contrapostas à evidência científica atual | H27: 46304 | I27: Não iniciado | J27: Contrapor as evidências dos informantes à evidência científica atual | K27: S5 | L27: AGJ | M27: 3 | N27: Mapeamento | O27: Backlog
A28: HIIP | B28: Background document - PHC | C28: Apresentado ao TWG-PHC; posição registada sobre o diagnóstico; ata com comentários e responsáveis; alterações incorporadas em versão datada | D28: 46332 | E28: Não iniciada | F28: Background document v1 | G28: Forma de apresentação aplicada; secção de contraste escrita; linguagem adequada ao cliente; evidências e referências revistas; revisão do country office resolvida | H28: 46318 | I28: Não iniciado | J28: Redigir a secção de contraste entre o que se acredita e o que se observou | K28: S5 | L28: AGJ | M28: 2 | N28: Síntese e mapeamento | O28: Backlog
... A32: HIIP | B32: Background document - PHC | C32: Apresentado ao TWG-PHC; posição registada sobre o diagnóstico; ata com comentários e responsáveis; alterações incorporadas em versão datada | D32: 46332 | E32: Não iniciada | F32: Background document v1 | G32: Forma de apresentação aplicada; secção de contraste escrita; linguagem adequada ao cliente; evidências e referências revistas; revisão do country office resolvida | H32: 46318 | I32: Não iniciado | J32: Revisão do country office | K32: S6 | L32: AGJ | M32: 2 | N32: Background document v1 | O32: Backlog
A33: HIIP | B33: Background document - PHC | C33: Apresentado ao TWG-PHC; posição registada sobre o diagnóstico; ata com comentários e responsáveis; alterações incorporadas em versão datada | D33: 46332 | E33: Não iniciada | J33: Apresentar o documento ao TWG-PHC para validação | K33: S6 | L33: AGJ | M33: 1 | N33: TWG-PHC refundado; Background v1 | O33: Backlog
A34: HIIP | B34: Background document - PHC | C34: Apresentado ao TWG-PHC; posição registada sobre o diagnóstico; ata com comentários e responsáveis; alterações incorporadas em versão datada | D34: 46332 | E34: Não iniciada | J34: Incorporar os comentários do TWG-PHC | K34: S7 | L34: AGJ | M34: 2 | N34: Sessão de validação | O34: Backlog

Sheet 3. Strategy document
A1: Strategy document - PHC
A3: Projeto | B3: Frente de trabalho (produto) | C3: Validação externa | D3: Data validação | E3: Estado validação | F3: Resultado (output) | G3: Definição de feito (resultado) | H3: Data resultado | I3: Estado resultado | J3: Tarefa | K3: Sprint | L3: Responsável | M3: Estimativa (dias) | N3: Depende de | O3: Estado tarefa | P3: Aprendizado
A4: HIIP | B4: Strategy document - PHC | C4: Apresentada ao TWG-PHC; posição registada sobre cada área priorizada (aceite/alterada/rejeitada); ata com decisões e responsáveis; MINSA confirma que serve de documento de política habilitante; alterações acordadas incorporadas em versão datada | D4: 46346 | E4: Não iniciada | F4: Mapa de barreiras, lacunas, gargalos e fortalezas | G4: Itens classificados por estrutura, processo e resultado e mapeados nas alavancas do framework; cada item com fonte identificada; intervenções candidatas com referência e nível de evidência | H4: 46304 | I4: Não iniciado | J4: Mapear barreiras, lacunas, gargalos e fortalezas por estrutura, processo e resultado | K4: S5 | L4: AGJ | M4: 4 | N4: Síntese qualitativa do campo | O4: Backlog
A5: HIIP | B5: Strategy document - PHC | C5: Apresentada ao TWG-PHC; posição registada sobre cada área priorizada (aceite/alterada/rejeitada); ata com decisões e responsáveis; MINSA confirma que serve de documento de política habilitante; alterações acordadas incorporadas em versão datada | D5: 46346 | E5: Não iniciada | F5: Mapa de barreiras, lacunas, gargalos e fortalezas | G5: Itens classificados por estrutura, processo e resultado e mapeados nas alavancas do framework; cada item com fonte identificada; intervenções candidatas com referência e nível de evidência | H5: 46304 | I5: Não iniciado | J5: Rever evidência de intervenções para cada barreira, lacuna e gargalo | K5: S5 | L5: AGJ | M5: 5 | N5: Mapa de barreiras | O5: Backlog
A6: HIIP | B6: Strategy document - PHC | C6: Apresentada ao TWG-PHC; posição registada sobre cada área priorizada (aceite/alterada/rejeitada); ata com decisões e responsáveis; MINSA confirma que serve de documento de política habilitante; alterações acordadas incorporadas em versão datada | D6: 46346 | E6: Não iniciada | F6: Teoria da mudança e leque de opções | G6: Cadeia barreira > intervenção > resultado explícita; cada opção com custo relativo, tempo até efeito e pré-condições; alternativas descartadas com a razão; áreas e ações candidatas à priorização identificadas | H6: 46304 | I6: Não iniciado | J6: Desenhar a teoria da mudança | K6: S5 | L6: AGJ | M6: 3 | N6: Tabela de evidência | O6: Backlog
A7: HIIP | B7: Strategy document - PHC | C7: Apresentada ao TWG-PHC; posição registada sobre cada área priorizada (aceite/alterada/rejeitada); ata com decisões e responsáveis; MINSA confirma que serve de documento de política habilitante; alterações acordadas incorporadas em versão datada | D7: 46346 | E7: Não iniciada | F7: Teoria da mudança e leque de opções | G7: Cadeia barreira > intervenção > resultado explícita; cada opção com custo relativo, tempo até efeito e pré-condições; alternativas descartadas com a razão; áreas e ações candidatas à priorização identificadas | H7: 46304 | I7: Não iniciado | J7: Construir o leque de opções para debate | K7: S5 | L7: AGJ | M7: 3 | N7: Teoria da mudança | O7: Backlog
A8: HIIP | B8: Strategy document - PHC | C8: Apresentada ao TWG-PHC; posição registada sobre cada área priorizada (aceite/alterada/rejeitada); ata com decisões e responsáveis; MINSA confirma que serve de documento de política habilitante; alterações acordadas incorporadas em versão datada | D8: 46346 | E8: Não iniciada | F8: Teoria da mudança e leque de opções | G8: Cadeia barreira > intervenção > resultado explícita; cada opção com custo relativo, tempo até efeito e pré-condições; alternativas descartadas com a razão; áreas e ações candidatas à priorização identificadas | H8: 46304 | I8: Não iniciado | J8: Identificação de áreas e ações para priorização | K8: S5 | L8: AGJ | M8: 3 | N8: Leque de opções | O8: Backlog
A9: HIIP | B9: Strategy document - PHC | C9: Apresentada ao TWG-PHC; posição registada sobre cada área priorizada (aceite/alterada/rejeitada); ata com decisões e responsáveis; MINSA confirma que serve de documento de política habilitante; alterações acordadas incorporadas em versão datada | D9: 46346 | E9: Não iniciada | F9: Estratégia v1 com áreas priorizadas | G9: Cobre todas as alavancas do framework; cada recomendação rastreável a uma barreira e à sua evidência; critério de priorização explícito; revisão do country office resolvida; versão em português pronta | H9: 46318 | I9: Não iniciado | J9: Redigir a estratégia v1 | K9: S5 | L9: AGJ | M9: 5 | N9: Áreas e ações priorizadas | O9: Backlog
A10: HIIP | B10: Strategy document - PHC | C10: Apresentada ao TWG-PHC; posição registada sobre cada área priorizada (aceite/alterada/rejeitada); ata com decisões e responsáveis; MINSA confirma que serve de documento de política habilitante; alterações acordadas incorporadas em versão datada | D10: 46346 | E10: Não iniciada | F10: Estratégia v1 com áreas priorizadas | G10: Cobre todas as alavancas do framework; cada recomendação rastreável a uma barreira e à sua evidência; critério de priorização explícito; revisão do country office resolvida; versão em português pronta | H10: 46318 | I10: Não iniciado | J10: Revisão interna e pré-alinhamento com o MINSA | K10: S6 | L10: AGJ | M10: 2 | N10: Estratégia v1 | O10: Backlog
A11: HIIP | B11: Strategy document - PHC | C11: Apresentada ao TWG-PHC; posição registada sobre cada área priorizada (aceite/alterada/rejeitada); ata com decisões e responsáveis; MINSA confirma que serve de documento de política habilitante; alterações acordadas incorporadas em versão datada | D11: 46346 | E11: Não iniciada | J11: Conduzir o policy dialogue de validação | K11: S7 | L11: AGJ | M11: 2 | N11: TWG-PHC refundado; Estratégia v1 | O11: Backlog
A12: HIIP | B12: Strategy document - PHC | C12: Apresentada ao TWG-PHC; posição registada sobre cada área priorizada (aceite/alterada/rejeitada); ata com decisões e responsáveis; MINSA confirma que serve de documento de política habilitante; alterações acordadas incorporadas em versão datada | D12: 46346 | E12: Não iniciada | J12: Incorporar as alterações acordadas | K12: S8 | L12: AGJ | M12: 3 | N12: Policy dialogue | O12: Backlog

Sheet 4. HHFA
A1: HHFA e diagnóstico situacional
A3: Projeto | B3: Frente de trabalho (produto) | C3: Validação externa | D3: Data validação | E3: Estado validação | F3: Resultado (output) | G3: Definição de feito (resultado) | H3: Data resultado | I3: Estado resultado | J3: Tarefa | K3: Sprint | L3: Responsável | M3: Estimativa (dias) | N3: Depende de | O3: Estado tarefa | P3: Aprendizado
A4: HIIP | B4: HHFA e diagnóstico situacional | C4: Relatório do HHFA apresentado e aceite; mecanismo rotineiro de avaliação estrutural proposto ao MINSA | D4: 46542 | E4: Não iniciada | F4: Acordo interagências | G4: Âmbito partilhado acordado; divisão de custos definida; acordo de cofinanciamento formalizado | H4: 46304 | I4: Em curso | J4: Manter as reuniões de alinhamento com o UNICEF e o UNFPA | K4: S3 | L4: AGJ | M4: 2 | O4: In progress
A5: HIIP | B5: HHFA e diagnóstico situacional | C5: Relatório do HHFA apresentado e aceite; mecanismo rotineiro de avaliação estrutural proposto ao MINSA | D5: 46542 | E5: Não iniciada | F5: Acordo interagências | G5: Âmbito partilhado acordado; divisão de custos definida; acordo de cofinanciamento formalizado | H5: 46304 | I5: Em curso | J5: Definir o âmbito partilhado e a divisão de custos | K5: S4 | L5: AGJ | M5: 2 | N5: Reuniões de alinhamento | O5: Backlog
A6: HIIP | B6: HHFA e diagnóstico situacional | C6: Relatório do HHFA apresentado e aceite; mecanismo rotineiro de avaliação estrutural proposto ao MINSA | D6: 46542 | E6: Não iniciada | F6: Acordo interagências | G6: Âmbito partilhado acordado; divisão de custos definida; acordo de cofinanciamento formalizado | H6: 46304 | I6: Em curso | J6: Formalizar o acordo de cofinanciamento | K6: S5 | L6: AGJ | M6: 2 | N6: Âmbito e custos definidos | O6: Backlog
A7: HIIP | B7: HHFA e diagnóstico situacional | C7: Relatório do HHFA apresentado e aceite; mecanismo rotineiro de avaliação estrutural proposto ao MINSA | D7: 46542 | E7: Não iniciada | F7: Adesão ao inquérito já contratado | G7: Amostra e ToR obtidos e analisados; lacunas face às perguntas do HIIP identificadas por escrito; margem de inclusão de itens confirmada com o UNFPA; cronograma de recolha conhecido e registado | H7: 46276 | I7: Não iniciado | J7: Obter e rever a amostragem, o ToR e o contrato já decididos | K7: S3 | L7: AGJ | M7: 1 | O7: Backlog
A8: HIIP | B8: HHFA e diagnóstico situacional | C8: Relatório do HHFA apresentado e aceite; mecanismo rotineiro de avaliação estrutural proposto ao MINSA | D8: 46542 | E8: Não iniciada | F8: Adesão ao inquérito já contratado | G8: Amostra e ToR obtidos e analisados; lacunas face às perguntas do HIIP identificadas por escrito; margem de inclusão de itens confirmada com o UNFPA; cronograma de recolha conhecido e registado | H8: 46276 | I8: Não iniciado | J8: Avaliar se a amostra serve às perguntas do diagnóstico dos CSP | K8: S3 | L8: AGJ | M8: 2 | N8: Amostragem obtida | O8: Backlog
A9: HIIP | B9: HHFA e diagnóstico situacional | C9: Relatório do HHFA apresentado e aceite; mecanismo rotineiro de avaliação estrutural proposto ao MINSA | D9: 46542 | E9: Não iniciada | F9: Adesão ao inquérito já contratado | G9: Amostra e ToR obtidos e analisados; lacunas face às perguntas do HIIP identificadas por escrito; margem de inclusão de itens confirmada com o UNFPA; cronograma de recolha conhecido e registado | H9: 46276 | I9: Não iniciado | J9: Identificar que margem existe para acrescentar itens ao instrumento | K9: S3 | L9: AGJ | M9: 1 | N9: Avaliação da amostra | O9: Backlog
A10: HIIP | B10: HHFA e diagnóstico situacional | C10: Relatório do HHFA apresentado e aceite; mecanismo rotineiro de avaliação estrutural proposto ao MINSA | D10: 46542 | E10: Não iniciada | F10: Adesão ao inquérito já contratado | G10: Amostra e ToR obtidos e analisados; lacunas face às perguntas do HIIP identificadas por escrito; margem de inclusão de itens confirmada com o UNFPA; cronograma de recolha conhecido e registado | H10: 46276 | I10: Não iniciado | J10: Participar na reunião de arranque com a empresa contratada | K10: S3 | L10: AGJ | M10: 1 | O10: Backlog
A11: HIIP | B11: HHFA e diagnóstico situacional | C11: Relatório do HHFA apresentado e aceite; mecanismo rotineiro de avaliação estrutural proposto ao MINSA | D11: 46542 | E11: Não iniciada | F11: Adesão ao inquérito já contratado | G11: Amostra e ToR obtidos e analisados; lacunas face às perguntas do HIIP identificadas por escrito; margem de inclusão de itens confirmada com o UNFPA; cronograma de recolha conhecido e registado | H11: 46276 | I11: Não iniciado | J11: Alinhar o cronograma de recolha com o calendário do HIIP | K11: S3 | L11: AGJ | M11: 1 | N11: Reunião de arranque | O11: Backlog
A12: HIIP | B12: HHFA e diagnóstico situacional | C12: Relatório do HHFA apresentado e aceite; mecanismo rotineiro de avaliação estrutural proposto ao MINSA | D12: 46542 | E12: Não iniciada | F12: Seleção de itens | G12: Itens do HHFA para o piloto selecionados com justificação; lista de itens sumários de estrutura, processo e resultado definida a partir do piloto | H12: 46304 | I12: Não iniciado | J12: Selecionar do HHFA os itens a capturar no piloto | K12: S3 | L12: AGJ | M12: 2 | N12: Margem de inclusão confirmada | O12: Backlog
A13: HIIP | B13: HHFA e diagnóstico situacional | C13: Relatório do HHFA apresentado e aceite; mecanismo rotineiro de avaliação estrutural proposto ao MINSA | D13: 46542 | E13: Não iniciada | F13: Seleção de itens | G13: Itens do HHFA para o piloto selecionados com justificação; lista de itens sumários de estrutura, processo e resultado definida a partir do piloto | H13: 46304 | I13: Não iniciado | J13: Definir a lista de itens sumários a partir do piloto | K13: S5 | L13: AGJ | M13: 3 | N13: Visitas piloto realizadas | O13: Backlog
A14: HIIP | B14: HHFA e diagnóstico situacional | C14: Relatório do HHFA apresentado e aceite; mecanismo rotineiro de avaliação estrutural proposto ao MINSA | D14: 46542 | E14: Não iniciada | F14: Instrumento | G14: Instrumento adaptado ao contexto angolano; programado no Kobo; pré-testado; desenho de métodos mistos sequencial exploratório documentado | H14: 46318 | I14: Não iniciado | J14: Adaptar o instrumento HHFA ao contexto angolano | K14: S6 | L14: AGJ | M14: 4 | N14: Lista de itens sumários | O14: Backlog
A15: HIIP | B15: HHFA e diagnóstico situacional | C15: Relatório do HHFA apresentado e aceite; mecanismo rotineiro de avaliação estrutural proposto ao MINSA | D15: 46542 | E15: Não iniciada | F15: Instrumento | G15: Instrumento adaptado ao contexto angolano; programado no Kobo; pré-testado; desenho de métodos mistos sequencial exploratório documentado | H15: 46318 | I15: Não iniciado | J15: Programar o instrumento no KoboToolbox | K15: S6 | L15: AGJ | M15: 2 | N15: Instrumento adaptado | O15: Backlog
A16: HIIP | B16: HHFA e diagnóstico situacional | C16: Relatório do HHFA apresentado e aceite; mecanismo rotineiro de avaliação estrutural proposto ao MINSA | D16: 46542 | E16: Não iniciada | F16: Instrumento | G16: Instrumento adaptado ao contexto angolano; programado no Kobo; pré-testado; desenho de métodos mistos sequencial exploratório documentado | H16: 46318 | I16: Não iniciado | J16: Pré-testar o instrumento | K16: S6 | L16: AGJ | M16: 1 | N16: Instrumento programado | O16: Backlog
A17: HIIP | B17: HHFA e diagnóstico situacional | C17: Relatório do HHFA apresentado e aceite; mecanismo rotineiro de avaliação estrutural proposto ao MINSA | D17: 46542 | E17: Não iniciada | F17: Instrumento | G17: Instrumento adaptado ao contexto angolano; programado no Kobo; pré-testado; desenho de métodos mistos sequencial exploratório documentado | H17: 46318 | I17: Não iniciado | J17: Documentar o desenho de métodos mistos sequencial exploratório | K17: S6 | L17: AGJ | M17: 2 | O17: Backlog
A18: HIIP | B18: HHFA e diagnóstico situacional | C18: Relatório do HHFA apresentado e aceite; mecanismo rotineiro de avaliação estrutural proposto ao MINSA | D18: 46542 | E18: Não iniciada | F18: Recolha | G18: Formação dos inquiridores acompanhada; recolha em curso conforme cronograma; qualidade monitorizada por vaga | H18: 46374 | I18: Não iniciado | J18: Acompanhar a formação dos inquiridores da empresa | K18: S7 | L18: AGJ | M18: 2 | N18: Instrumento pré-testado | O18: Backlog
A19: HIIP | B19: HHFA e diagnóstico situacional | C19: Relatório do HHFA apresentado e aceite; mecanismo rotineiro de avaliação estrutural proposto ao MINSA | D19: 46542 | E19: Não iniciada | F19: Recolha | G19: Formação dos inquiridores acompanhada; recolha em curso conforme cronograma; qualidade monitorizada por vaga | H19: 46374 | I19: Não iniciado | J19: Acompanhar a logística de terreno | K19: S7 | L19: AGJ | M19: 1 | O19: Backlog
A20: HIIP | B20: HHFA e diagnóstico situacional | C20: Relatório do HHFA apresentado e aceite; mecanismo rotineiro de avaliação estrutural proposto ao MINSA | D20: 46542 | E20: Não iniciada | F20: Recolha | G20: Formação dos inquiridores acompanhada; recolha em curso conforme cronograma; qualidade monitorizada por vaga | H20: 46374 | I20: Não iniciado | J20: Monitorizar a qualidade dos dados por vaga | K20: Recorrente | L20: AGJ | M20: 1 | N20: Recolha em curso | O20: Backlog
A21: HIIP | B21: HHFA e diagnóstico situacional | C21: Relatório do HHFA apresentado e aceite; mecanismo rotineiro de avaliação estrutural proposto ao MINSA | D21: 46542 | E21: Não iniciada | F21: Análise | G21: Base limpa e documentada; análise concluída; relatório do HHFA redigido | H21: 46430 | I21: Não iniciado | J21: Limpar e organizar a base de dados | K21: S12 | L21: AGJ | M21: 3 | N21: Recolha concluída | O21: Backlog
A22: HIIP | B22: HHFA e diagnóstico situacional | C22: Relatório do HHFA apresentado e aceite; mecanismo rotineiro de avaliação estrutural proposto ao MINSA | D22: 46542 | E22: Não iniciada | F22: Análise | G22: Base limpa e documentada; análise concluída; relatório do HHFA redigido | H22: 46430 | I22: Não iniciado | J22: Analisar os dados | K22: S12 | L22: AGJ | M22: 5 | N22: Base limpa | O22: Backlog
A23: HIIP | B23: HHFA e diagnóstico situacional | C23: Relatório do HHFA apresentado e aceite; mecanismo rotineiro de avaliação estrutural proposto ao MINSA | D23: 46542 | E23: Não iniciada | F23: Análise | G23: Base limpa e documentada; análise concluída; relatório do HHFA redigido | H23: 46430 | I23: Não iniciado | J23: Redigir o relatório do HHFA | K23: S13 | L23: AGJ | M23: 5 | N23: Análise | O23: Backlog
A24: HIIP | B24: HHFA e diagnóstico situacional | C24: Relatório do HHFA apresentado e aceite; mecanismo rotineiro de avaliação estrutural proposto ao MINSA | D24: 46542 | E24: Não iniciada | F24: Legado | G24: Mecanismo rotineiro de avaliação estrutural desenhado; proposta submetida ao MINSA | H24: 46542 | I24: Não iniciado | J24: Desenhar o mecanismo rotineiro de avaliação estrutural | K24: S13 | L24: AGJ | M24: 4 | N24: Relatório do HHFA | O24: Backlog
A25: HIIP | B25: HHFA e diagnóstico situacional | C25: Relatório do HHFA apresentado e aceite; mecanismo rotineiro de avaliação estrutural proposto ao MINSA | D25: 46542 | E25: Não iniciada | F25: Legado | G25: Mecanismo rotineiro de avaliação estrutural desenhado; proposta submetida ao MINSA | H25: 46542 | I25: Não iniciado | J25: Propor o mecanismo ao MINSA | K25: S14 | L25: AGJ | M25: 2 | N25: Mecanismo desenhado | O25: Backlog

Sheet 5. PFM
A1: PFM
A3: Projeto | B3: Frente de trabalho (produto) | C3: Validação externa | D3: Data validação | E3: Estado validação | F3: Resultado (output) | G3: Definição de feito (resultado) | H3: Data resultado | I3: Estado resultado | J3: Tarefa | K3: Sprint | L3: Responsável | M3: Estimativa (dias) | N3: Depende de | O3: Estado tarefa | P3: Aprendizado
A4: HIIP | B4: PFM | C4: Diagnóstico apresentado ao TWG-PFM; posição registada; ata com decisões; alterações incorporadas em versão datada | D4: 46444 | E4: Não iniciada | F4: TWG-PFM constituído | G4: ToR aprovado pelo MINSA; lista de membros confirmada; relatório das entrevistas partilhado; ata da sessão inaugural com plano de trabalho acordado | H4: 46290 | I4: Em curso | J4: Finalizar o ToR do TWG-PFM | K4: S1 | L4: AGJ | M4: 2 | O4: Done
A5: HIIP | B5: PFM | C5: Diagnóstico apresentado ao TWG-PFM; posição registada; ata com decisões; alterações incorporadas em versão datada | D5: 46444 | E5: Não iniciada | F5: TWG-PFM constituído | G5: ToR aprovado pelo MINSA; lista de membros confirmada; relatório das entrevistas partilhado; ata da sessão inaugural com plano de trabalho acordado | H5: 46290 | I5: Em curso | J5: Confirmar a lista de participantes | K5: S2 | L5: AGJ | M5: 2 | N5: ToR | O5: Done
A6: HIIP | B6: PFM | C6: Diagnóstico apresentado ao TWG-PFM; posição registada; ata com decisões; alterações incorporadas em versão datada | D6: 46444 | E6: Não iniciada | F6: TWG-PFM constituído | G6: ToR aprovado pelo MINSA; lista de membros confirmada; relatório das entrevistas partilhado; ata da sessão inaugural com plano de trabalho acordado | H6: 46290 | I6: Em curso | J6: Organizar o cronograma e enviar os convites | K6: S3 | L6: AGJ | M6: 2 | N6: Lista de participantes | O6: In progress
A7: HIIP | B7: PFM | C7: Diagnóstico apresentado ao TWG-PFM; posição registada; ata com decisões; alterações incorporadas em versão datada | D7: 46444 | E7: Não iniciada | F7: TWG-PFM constituído | G7: ToR aprovado pelo MINSA; lista de membros confirmada; relatório das entrevistas partilhado; ata da sessão inaugural com plano de trabalho acordado | H7: 46290 | I7: Em curso | J7: Conduzir as entrevistas preparatórias com os membros | K7: S3 | L7: AGJ | M7: 4 | N7: Convites | O7: Backlog
A8: HIIP | B8: PFM | C8: Diagnóstico apresentado ao TWG-PFM; posição registada; ata com decisões; alterações incorporadas em versão datada | D8: 46444 | E8: Não iniciada | F8: TWG-PFM constituído | G8: ToR aprovado pelo MINSA; lista de membros confirmada; relatório das entrevistas partilhado; ata da sessão inaugural com plano de trabalho acordado | H8: 46290 | I8: Em curso | J8: Produzir o relatório das entrevistas preparatórias | K8: S4 | L8: AGJ | M8: 3 | N8: Entrevistas preparatórias | O8: Backlog
A9: HIIP | B9: PFM | C9: Diagnóstico apresentado ao TWG-PFM; posição registada; ata com decisões; alterações incorporadas em versão datada | D9: 46444 | E9: Não iniciada | F9: TWG-PFM constituído | G9: ToR aprovado pelo MINSA; lista de membros confirmada; relatório das entrevistas partilhado; ata da sessão inaugural com plano de trabalho acordado | H9: 46290 | I9: Em curso | J9: Conduzir a sessão inaugural | K9: S4 | L9: AGJ | M9: 1 | N9: Relatório das entrevistas | O9: Backlog
A10: HIIP | B10: PFM | C10: Diagnóstico apresentado ao TWG-PFM; posição registada; ata com decisões; alterações incorporadas em versão datada | D10: 46444 | E10: Não iniciada | F10: TWG-PFM constituído | G10: ToR aprovado pelo MINSA; lista de membros confirmada; relatório das entrevistas partilhado; ata da sessão inaugural com plano de trabalho acordado | H10: 46290 | I10: Em curso | J10: Acordar o plano de trabalho e o calendário quinzenal | K10: S4 | L10: AGJ | M10: 1 | N10: Sessão inaugural | O10: Backlog
A11: HIIP | B11: PFM | C11: Diagnóstico apresentado ao TWG-PFM; posição registada; ata com decisões; alterações incorporadas em versão datada | D11: 46444 | E11: Não iniciada | F11: Consultoria PFM contratada | G11: ToR aprovado; contrato assinado; especialista local integrado; relatório de arranque aceite | H11: 46332 | I11: Não iniciado | J11: Reunião com o Banco Mundial sobre o financiamento do especialista local | K11: S3 | L11: AGJ | M11: 1 | O11: Backlog
A12: HIIP | B12: PFM | C12: Diagnóstico apresentado ao TWG-PFM; posição registada; ata com decisões; alterações incorporadas em versão datada | D12: 46444 | E12: Não iniciada | F12: Consultoria PFM contratada | G12: ToR aprovado; contrato assinado; especialista local integrado; relatório de arranque aceite | H12: 46332 | I12: Não iniciado | J12: Redigir o ToR e as especificações da consultoria | K12: S4 | L12: AGJ | M12: 3 | N12: Relatório das entrevistas | O12: Backlog
A13: HIIP | B13: PFM | C13: Diagnóstico apresentado ao TWG-PFM; posição registada; ata com decisões; alterações incorporadas em versão datada | D13: 46444 | E13: Não iniciada | F13: Consultoria PFM contratada | G13: ToR aprovado; contrato assinado; especialista local integrado; relatório de arranque aceite | H13: 46332 | I13: Não iniciado | J13: Conduzir o processo de seleção | K13: S5 | L13: AGJ | M13: 5 | N13: ToR da consultoria | O13: Backlog
A14: HIIP | B14: PFM | C14: Diagnóstico apresentado ao TWG-PFM; posição registada; ata com decisões; alterações incorporadas em versão datada | D14: 46444 | E14: Não iniciada | F14: Consultoria PFM contratada | G14: ToR aprovado; contrato assinado; especialista local integrado; relatório de arranque aceite | H14: 46332 | I14: Não iniciado | J14: Contratar a consultoria | K14: S6 | L14: AGJ | M14: 2 | N14: Processo de seleção | O14: Backlog
A15: HIIP | B15: PFM | C15: Diagnóstico apresentado ao TWG-PFM; posição registada; ata com decisões; alterações incorporadas em versão datada | D15: 46444 | E15: Não iniciada | F15: Consultoria PFM contratada | G15: ToR aprovado; contrato assinado; especialista local integrado; relatório de arranque aceite | H15: 46332 | I15: Não iniciado | J15: Integrar o especialista local | K15: S6 | L15: AGJ | M15: 3 | N15: Acordo com o Banco Mundial | O15: Backlog
A16: HIIP | B16: PFM | C16: Diagnóstico apresentado ao TWG-PFM; posição registada; ata com decisões; alterações incorporadas em versão datada | D16: 46444 | E16: Não iniciada | F16: Consultoria PFM contratada | G16: ToR aprovado; contrato assinado; especialista local integrado; relatório de arranque aceite | H16: 46332 | I16: Não iniciado | J16: Reunião de arranque e validação do plano de trabalho | K16: S7 | L16: AGJ | M16: 2 | N16: Contrato assinado | O16: Backlog
A17: HIIP | B17: PFM | C17: Diagnóstico apresentado ao TWG-PFM; posição registada; ata com decisões; alterações incorporadas em versão datada | D17: 46444 | E17: Não iniciada | F17: Condução da consultoria | G17: Reuniões quinzenais realizadas com ata; primeiro rascunho revisto; relatório final aceite | H17: 46430 | I17: Não iniciado | J17: Conduzir as reuniões quinzenais do TWG-PFM | K17: Recorrente | L17: AGJ | M17: 1 | N17: Sessão inaugural | O17: Backlog
A18: HIIP | B18: PFM | C18: Diagnóstico apresentado ao TWG-PFM; posição registada; ata com decisões; alterações incorporadas em versão datada | D18: 46444 | E18: Não iniciada | F18: Condução da consultoria | G18: Reuniões quinzenais realizadas com ata; primeiro rascunho revisto; relatório final aceite | H18: 46430 | I18: Não iniciado | J18: Supervisionar as entrevistas e atividades com o grupo | K18: Recorrente | L18: AGJ | M18: 2 | N18: Reunião de arranque | O18: Backlog
A19: HIIP | B19: PFM | C19: Diagnóstico apresentado ao TWG-PFM; posição registada; ata com decisões; alterações incorporadas em versão datada | D19: 46444 | E19: Não iniciada | F19: Condução da consultoria | G19: Reuniões quinzenais realizadas com ata; primeiro rascunho revisto; relatório final aceite | H19: 46430 | I19: Não iniciado | J19: Rever o primeiro rascunho da consultoria | K19: S9 | L19: AGJ | M19: 2 | N19: Consultoria em curso | O19: Backlog
A20: HIIP | B20: PFM | C20: Diagnóstico apresentado ao TWG-PFM; posição registada; ata com decisões; alterações incorporadas em versão datada | D20: 46444 | E20: Não iniciada | F20: Condução da consultoria | G20: Reuniões quinzenais realizadas com ata; primeiro rascunho revisto; relatório final aceite | H20: 46430 | I20: Não iniciado | J20: Rever e aceitar o relatório final | K20: S13 | L20: AGJ | M20: 3 | N20: Primeiro rascunho | O20: Backlog
A21: HIIP | B21: PFM | C21: Diagnóstico apresentado ao TWG-PFM; posição registada; ata com decisões; alterações incorporadas em versão datada | D21: 46444 | E21: Não iniciada | F21: Alinhamento com parceiros | G21: Divisão de trabalho documentada com o UNDP e o Banco Mundial | H21: 46346 | I21: Não iniciado | J21: Alinhar com o UNDP e o Banco Mundial sobre as frentes de modernização da GFP | K21: S4 | L21: AGJ | M21: 2 | O21: Backlog
A22: HIIP | B22: PFM | C22: Diagnóstico apresentado ao TWG-PFM; posição registada; ata com decisões; alterações incorporadas em versão datada | D22: 46444 | E22: Não iniciada | F22: Alinhamento com parceiros | G22: Divisão de trabalho documentada com o UNDP e o Banco Mundial | H22: 46346 | I22: Não iniciado | J22: Documentar a divisão de trabalho entre as três instituições | K22: S8 | L22: AGJ | M22: 1 | N22: Alinhamento | O22: Backlog
A23: HIIP | B23: PFM | C23: Diagnóstico apresentado ao TWG-PFM; posição registada; ata com decisões; alterações incorporadas em versão datada | D23: 46444 | E23: Não iniciada | J23: Apresentar o diagnóstico ao TWG-PFM para validação | K23: S14 | L23: AGJ | M23: 1 | N23: Relatório final | O23: Backlog

Sheet 6. Investment case
A1: Investment case - PHC
A3: Projeto | B3: Frente de trabalho (produto) | C3: Validação externa | D3: Data validação | E3: Estado validação | F3: Resultado (output) | G3: Definição de feito (resultado) | H3: Data resultado | I3: Estado resultado | J3: Tarefa | K3: Sprint | L3: Responsável | M3: Estimativa (dias) | N3: Depende de | O3: Estado tarefa | P3: Aprendizado
A4: HIIP | B4: Investment case - PHC | C4: Duas validações: diálogo no MINSA com a Ministra sobre a v1 (06/11/2026); validação técnica da v2, com HHFA, pelo TWG-PHC (26/02/2027) | D4: 46444 | E4: Não iniciada | F4: Estrutura e estratégia de materialização | G4: Estrutura do documento acordada internamente; atores-chave identificados por posição e influência; sequência de conversas planeada até novembro | H4: 46304 | I4: Não iniciado | J4: Definir a estrutura do investment case | K4: S5 | L4: AGJ | M4: 2 | O4: Backlog
A5: HIIP | B5: Investment case - PHC | C5: Duas validações: diálogo no MINSA com a Ministra sobre a v1 (06/11/2026); validação técnica da v2, com HHFA, pelo TWG-PHC (26/02/2027) | D5: 46444 | E5: Não iniciada | F5: Estrutura e estratégia de materialização | G5: Estrutura do documento acordada internamente; atores-chave identificados por posição e influência; sequência de conversas planeada até novembro | H5: 46304 | I5: Não iniciado | J5: Identificar os atores cujo apoio dá poder ao documento dentro do MINSA | K5: S5 | L5: AGJ | M5: 2 | O5: Backlog
A6: HIIP | B6: Investment case - PHC | C6: Duas validações: diálogo no MINSA com a Ministra sobre a v1 (06/11/2026); validação técnica da v2, com HHFA, pelo TWG-PHC (26/02/2027) | D6: 46444 | E6: Não iniciada | F6: Estrutura e estratégia de materialização | G6: Estrutura do documento acordada internamente; atores-chave identificados por posição e influência; sequência de conversas planeada até novembro | H6: 46304 | I6: Não iniciado | J6: Planear o engajamento desses atores ao longo da produção | K6: S5 | L6: AGJ | M6: 2 | N6: Atores identificados | O6: Backlog
A7: HIIP | B7: Investment case - PHC | C7: Duas validações: diálogo no MINSA com a Ministra sobre a v1 (06/11/2026); validação técnica da v2, com HHFA, pelo TWG-PHC (26/02/2027) | D7: 46444 | E7: Não iniciada | F7: Base de evidência financeira | G7: Dados de financiamento reunidos com fonte e data de extração; mapeamento de doadores obtido do project scoping; lacuna de financiamento estimada em ordem de grandeza | H7: 46318 | I7: Não iniciado | J7: Reunir os dados de financiamento disponíveis | K7: S6 | L7: AGJ | M7: 3 | O7: Backlog
A8: HIIP | B8: Investment case - PHC | C8: Duas validações: diálogo no MINSA com a Ministra sobre a v1 (06/11/2026); validação técnica da v2, com HHFA, pelo TWG-PHC (26/02/2027) | D8: 46444 | E8: Não iniciada | F8: Base de evidência financeira | G8: Dados de financiamento reunidos com fonte e data de extração; mapeamento de doadores obtido do project scoping; lacuna de financiamento estimada em ordem de grandeza | H8: 46318 | I8: Não iniciado | J8: Obter do project scoping o mapeamento de projetos e doadores | K8: S6 | L8: AGJ | M8: 1 | N8: Mapeamento de doadores | O8: Backlog
A9: HIIP | B9: Investment case - PHC | C9: Duas validações: diálogo no MINSA com a Ministra sobre a v1 (06/11/2026); validação técnica da v2, com HHFA, pelo TWG-PHC (26/02/2027) | D9: 46444 | E9: Não iniciada | F9: Base de evidência financeira | G9: Dados de financiamento reunidos com fonte e data de extração; mapeamento de doadores obtido do project scoping; lacuna de financiamento estimada em ordem de grandeza | H9: 46318 | I9: Não iniciado | J9: Estimar a lacuna de financiamento dos CSP em ordem de grandeza | K9: S6 | L9: AGJ | M9: 3 | N9: Dados de financiamento | O9: Backlog
A10: HIIP | B10: Investment case - PHC | C10: Duas validações: diálogo no MINSA com a Ministra sobre a v1 (06/11/2026); validação técnica da v2, com HHFA, pelo TWG-PHC (26/02/2027) | D10: 46444 | E10: Não iniciada | F10: Investment case v1 | G10: Narrativa por área priorizada escrita; revisão do country office resolvida; versão datada e pronta para o diálogo com a Ministra | H10: 46332 | I10: Não iniciado | J10: Escrever a narrativa de investimento por área priorizada | K10: S6 | L10: AGJ | M10: 4 | N10: Estratégia v1; base de evidência | O10: Backlog
A11: HIIP | B11: Investment case - PHC | C11: Duas validações: diálogo no MINSA com a Ministra sobre a v1 (06/11/2026); validação técnica da v2, com HHFA, pelo TWG-PHC (26/02/2027) | D11: 46444 | E11: Não iniciada | F11: Investment case v1 | G11: Narrativa por área priorizada escrita; revisão do country office resolvida; versão datada e pronta para o diálogo com a Ministra | H11: 46332 | I11: Não iniciado | J11: Redigir o investment case v1 | K11: S7 | L11: AGJ | M11: 5 | N11: Narrativa de investimento | O11: Backlog
A12: HIIP | B12: Investment case - PHC | C12: Duas validações: diálogo no MINSA com a Ministra sobre a v1 (06/11/2026); validação técnica da v2, com HHFA, pelo TWG-PHC (26/02/2027) | D12: 46444 | E12: Não iniciada | F12: Investment case v1 | G12: Narrativa por área priorizada escrita; revisão do country office resolvida; versão datada e pronta para o diálogo com a Ministra | H12: 46332 | I12: Não iniciado | J12: Revisão do country office | K12: S7 | L12: AGJ | M12: 2 | N12: Investment case v1 | O12: Backlog
A13: HIIP | B13: Investment case - PHC | C13: Duas validações: diálogo no MINSA com a Ministra sobre a v1 (06/11/2026); validação técnica da v2, com HHFA, pelo TWG-PHC (26/02/2027) | D13: 46444 | E13: Não iniciada | F13: Investment case v2 com HHFA | G13: Achados do HHFA incorporados; números revistos; versão datada | H13: 46444 | I13: Não iniciado | J13: Incorporar os achados do HHFA | K13: S14 | L13: AGJ | M13: 4 | N13: Relatório do HHFA | O13: Backlog
A14: HIIP | B14: Investment case - PHC | C14: Duas validações: diálogo no MINSA com a Ministra sobre a v1 (06/11/2026); validação técnica da v2, com HHFA, pelo TWG-PHC (26/02/2027) | D14: 46444 | E14: Não iniciada | F14: Investment case v2 com HHFA | G14: Achados do HHFA incorporados; números revistos; versão datada | H14: 46444 | I14: Não iniciado | J14: Rever os números e a narrativa | K14: S14 | L14: AGJ | M14: 2 | N14: Achados do HHFA incorporados | O14: Backlog
A15: HIIP | B15: Investment case - PHC | C15: Duas validações: diálogo no MINSA com a Ministra sobre a v1 (06/11/2026); validação técnica da v2, com HHFA, pelo TWG-PHC (26/02/2027) | D15: 46444 | E15: Não iniciada | J15: Apresentar a v1 no diálogo interno do MINSA, com a Ministra | K15: S7 | L15: AGJ | M15: 1 | N15: Investment case v1 | O15: Backlog
A16: HIIP | B16: Investment case - PHC | C16: Duas validações: diálogo no MINSA com a Ministra sobre a v1 (06/11/2026); validação técnica da v2, com HHFA, pelo TWG-PHC (26/02/2027) | D16: 46444 | E16: Não iniciada | J16: Apresentar a v2 ao TWG-PHC para validação | K16: S14 | L16: AGJ | M16: 1 | N16: Investment case v2 | O16: Backlog

Sheet 7. Investment plan
A1: PHC investment plan (custeado)
A3: Projeto | B3: Frente de trabalho (produto) | C3: Validação externa | D3: Data validação | E3: Estado validação | F3: Resultado (output) | G3: Definição de feito (resultado) | H3: Data resultado | I3: Estado resultado | J3: Tarefa | K3: Sprint | L3: Responsável | M3: Estimativa (dias) | N3: Depende de | O3: Estado tarefa | P3: Aprendizado
A4: HIIP | B4: PHC investment plan (custeado) | C4: Plano validado pelo TWG-PHC; posição registada; alterações incorporadas em versão datada | D4: 46472 | E4: Não iniciada | F4: Consenso sobre áreas de investimento | G4: Buy-in dos stakeholders registado; priorização técnica concluída; consenso político obtido; devido processo dentro do governo seguido e documentado | H4: 46346 | I4: Não iniciado | J4: Obter o buy-in dos stakeholders sobre as áreas geográficas e temáticas | K4: S8 | L4: AGJ | M4: 4 | N4: Estratégia validada | O4: Backlog
A5: HIIP | B5: PHC investment plan (custeado) | C5: Plano validado pelo TWG-PHC; posição registada; alterações incorporadas em versão datada | D5: 46472 | E5: Não iniciada | F5: Consenso sobre áreas de investimento | G5: Buy-in dos stakeholders registado; priorização técnica concluída; consenso político obtido; devido processo dentro do governo seguido e documentado | H5: 46346 | I5: Não iniciado | J5: Conduzir a priorização técnica | K5: S8 | L5: AGJ | M5: 4 | N5: Buy-in dos stakeholders | O5: Backlog
A6: HIIP | B6: PHC investment plan (custeado) | C6: Plano validado pelo TWG-PHC; posição registada; alterações incorporadas em versão datada | D6: 46472 | E6: Não iniciada | F6: Consenso sobre áreas de investimento | G6: Buy-in dos stakeholders registado; priorização técnica concluída; consenso político obtido; devido processo dentro do governo seguido e documentado | H6: 46346 | I6: Não iniciado | J6: Construir o consenso político | K6: S8 | L6: AGJ | M6: 3 | N6: Priorização técnica | O6: Backlog
A7: HIIP | B7: PHC investment plan (custeado) | C7: Plano validado pelo TWG-PHC; posição registada; alterações incorporadas em versão datada | D7: 46472 | E7: Não iniciada | F7: Consenso sobre áreas de investimento | G7: Buy-in dos stakeholders registado; priorização técnica concluída; consenso político obtido; devido processo dentro do governo seguido e documentado | H7: 46346 | I7: Não iniciado | J7: Seguir o devido processo dentro do governo | K7: Recorrente | L7: AGJ | M7: 2 | N7: Consenso político | O7: Backlog
A8: HIIP | B8: PHC investment plan (custeado) | C8: Plano validado pelo TWG-PHC; posição registada; alterações incorporadas em versão datada | D8: 46472 | E8: Não iniciada | F8: Evidência financeira | G8: Contas nacionais de saúde mapeadas; verificação do resource tracking do Banco Mundial concluída; matriz de resource tracking de doadores construída | H8: 46360 | I8: Não iniciado | J8: Mapear as contas nacionais de saúde relevantes para os CSP | K8: S8 | L8: AGJ | M8: 4 | O8: Backlog
A9: HIIP | B9: PHC investment plan (custeado) | C9: Plano validado pelo TWG-PHC; posição registada; alterações incorporadas em versão datada | D9: 46472 | E9: Não iniciada | F9: Evidência financeira | G9: Contas nacionais de saúde mapeadas; verificação do resource tracking do Banco Mundial concluída; matriz de resource tracking de doadores construída | H9: 46360 | I9: Não iniciado | J9: Verificar se o Banco Mundial fez resource tracking e obter os dados | K9: S8 | L9: AGJ | M9: 1 | O9: Backlog
A10: HIIP | B10: PHC investment plan (custeado) | C10: Plano validado pelo TWG-PHC; posição registada; alterações incorporadas em versão datada | D10: 46472 | E10: Não iniciada | F10: Evidência financeira | G10: Contas nacionais de saúde mapeadas; verificação do resource tracking do Banco Mundial concluída; matriz de resource tracking de doadores construída | H10: 46360 | I10: Não iniciado | J10: Construir a matriz de resource tracking de doadores | K10: S9 | L10: AGJ | M10: 5 | N10: Verificação do resource tracking | O10: Backlog
A11: HIIP | B11: PHC investment plan (custeado) | C11: Plano validado pelo TWG-PHC; posição registada; alterações incorporadas em versão datada | D11: 46472 | E11: Não iniciada | F11: Planeamento de implementação | G11: Exercícios de planeamento realizados por área; deep dive documentado; pacotes de investimento definidos e traduzidos em planos de ação | H11: 46416 | I11: Não iniciado | J11: Conduzir os exercícios de planeamento de ação por área de investimento | K11: S10 | L11: AGJ | M11: 5 | N11: Consenso sobre áreas | O11: Backlog
A12: HIIP | B12: PHC investment plan (custeado) | C12: Plano validado pelo TWG-PHC; posição registada; alterações incorporadas em versão datada | D12: 46472 | E12: Não iniciada | F12: Planeamento de implementação | G12: Exercícios de planeamento realizados por área; deep dive documentado; pacotes de investimento definidos e traduzidos em planos de ação | H12: 46416 | I12: Não iniciado | J12: Conduzir o deep dive de implementação por área | K12: S11 | L12: AGJ | M12: 8 | N12: Exercícios de planeamento | O12: Backlog
A13: HIIP | B13: PHC investment plan (custeado) | C13: Plano validado pelo TWG-PHC; posição registada; alterações incorporadas em versão datada | D13: 46472 | E13: Não iniciada | F13: Planeamento de implementação | G13: Exercícios de planeamento realizados por área; deep dive documentado; pacotes de investimento definidos e traduzidos em planos de ação | H13: 46416 | I13: Não iniciado | J13: Definir os pacotes de investimento e traduzi-los em planos de ação | K13: S12 | L13: AGJ | M13: 5 | N13: Deep dive | O13: Backlog
A14: HIIP | B14: PHC investment plan (custeado) | C14: Plano validado pelo TWG-PHC; posição registada; alterações incorporadas em versão datada | D14: 46472 | E14: Não iniciada | F14: Custeio e projeção | G14: Pacotes de investimento custeados; necessidades de financiamento e coordenação de doadores projetadas | H14: 46444 | I14: Não iniciado | J14: Custear os pacotes de investimento | K14: S13 | L14: AGJ | M14: 8 | N14: Pacotes definidos | O14: Backlog
A15: HIIP | B15: PHC investment plan (custeado) | C15: Plano validado pelo TWG-PHC; posição registada; alterações incorporadas em versão datada | D15: 46472 | E15: Não iniciada | F15: Custeio e projeção | G15: Pacotes de investimento custeados; necessidades de financiamento e coordenação de doadores projetadas | H15: 46444 | I15: Não iniciado | J15: Projetar necessidades de financiamento e coordenação de doadores | K15: S14 | L15: AGJ | M15: 4 | N15: Custeio; matriz de resource tracking | O15: Backlog
A16: HIIP | B16: PHC investment plan (custeado) | C16: Plano validado pelo TWG-PHC; posição registada; alterações incorporadas em versão datada | D16: 46472 | E16: Não iniciada | F16: Investment plan | G16: Plano v1 consolidado; revisão pós-validação feita; plano final entregue ao MINSA | H16: 46542 | I16: Não iniciado | J16: Consolidar o investment plan v1 | K16: S15 | L16: AGJ | M16: 6 | N16: Custeio e projeção | O16: Backlog
A17: HIIP | B17: PHC investment plan (custeado) | C17: Plano validado pelo TWG-PHC; posição registada; alterações incorporadas em versão datada | D17: 46472 | E17: Não iniciada | F17: Investment plan | G17: Plano v1 consolidado; revisão pós-validação feita; plano final entregue ao MINSA | H17: 46542 | I17: Não iniciado | J17: Revisão pós-validação e entrega ao MINSA | K17: S20 | L17: AGJ | M17: 4 | N17: Validação; reuniões de doadores | O17: Backlog
A18: HIIP | B18: PHC investment plan (custeado) | C18: Plano validado pelo TWG-PHC; posição registada; alterações incorporadas em versão datada | D18: 46472 | E18: Não iniciada | J18: Conduzir o policy dialogue de validação do investment plan | K18: S16 | L18: AGJ | M18: 2 | N18: Investment plan v1 | O18: Backlog

Sheet 8. Essential package
A1: Essential package - PHC
A3: Projeto | B3: Frente de trabalho (produto) | C3: Validação externa | D3: Data validação | E3: Estado validação | F3: Resultado (output) | G3: Definição de feito (resultado) | H3: Data resultado | I3: Estado resultado | J3: Tarefa | K3: Sprint | L3: Responsável | M3: Estimativa (dias) | N3: Depende de | O3: Estado tarefa | P3: Aprendizado
A4: HIIP | B4: Essential package - PHC | C4: Pacote essencial apresentado ao TWG-PHC; posição registada; alterações incorporadas em versão datada | D4: 46402 | E4: Não iniciada | F4: Critérios e âmbito | G4: Critérios de inclusão de serviços definidos; âmbito delimitado por nível de unidade sanitária | H4: 46346 | I4: Não iniciado | J4: Definir os critérios de inclusão de serviços no pacote | K4: S8 | L4: AGJ | M4: 3 | N4: Estratégia validada | O4: Backlog
A5: HIIP | B5: Essential package - PHC | C5: Pacote essencial apresentado ao TWG-PHC; posição registada; alterações incorporadas em versão datada | D5: 46402 | E5: Não iniciada | F5: Critérios e âmbito | G5: Critérios de inclusão de serviços definidos; âmbito delimitado por nível de unidade sanitária | H5: 46346 | I5: Não iniciado | J5: Delimitar o âmbito por nível de unidade sanitária | K5: S8 | L5: AGJ | M5: 2 | N5: Critérios de inclusão | O5: Backlog
A6: HIIP | B6: Essential package - PHC | C6: Pacote essencial apresentado ao TWG-PHC; posição registada; alterações incorporadas em versão datada | D6: 46402 | E6: Não iniciada | F6: Seleção a partir do UHC Compendium | G6: Intervenções filtradas para o nível dos CSP; seleção adequada ao perfil epidemiológico e à capacidade instalada; confronto com a oferta atual documentado | H6: 46360 | I6: Não iniciado | J6: Filtrar do UHC Compendium as intervenções aplicáveis ao nível dos CSP | K6: S9 | L6: AGJ | M6: 3 | N6: Critérios e âmbito | O6: Backlog
A7: HIIP | B7: Essential package - PHC | C7: Pacote essencial apresentado ao TWG-PHC; posição registada; alterações incorporadas em versão datada | D7: 46402 | E7: Não iniciada | F7: Seleção a partir do UHC Compendium | G7: Intervenções filtradas para o nível dos CSP; seleção adequada ao perfil epidemiológico e à capacidade instalada; confronto com a oferta atual documentado | H7: 46360 | I7: Não iniciado | J7: Adequar a seleção ao perfil epidemiológico e à capacidade instalada em Angola | K7: S9 | L7: AGJ | M7: 3 | N7: Seleção do compendium | O7: Backlog
A8: HIIP | B8: Essential package - PHC | C8: Pacote essencial apresentado ao TWG-PHC; posição registada; alterações incorporadas em versão datada | D8: 46402 | E8: Não iniciada | F8: Seleção a partir do UHC Compendium | G8: Intervenções filtradas para o nível dos CSP; seleção adequada ao perfil epidemiológico e à capacidade instalada; confronto com a oferta atual documentado | H8: 46360 | I8: Não iniciado | J8: Confrontar a seleção com o que as unidades efetivamente ofertam hoje | K8: S9 | L8: AGJ | M8: 2 | N8: Piloto; HHFA | O8: Backlog
A9: HIIP | B9: Essential package - PHC | C9: Pacote essencial apresentado ao TWG-PHC; posição registada; alterações incorporadas em versão datada | D9: 46402 | E9: Não iniciada | F9: Pacote essencial v1 | G9: Pacote redigido; implicações de recursos estimadas por serviço incluído | H9: 46374 | I9: Não iniciado | J9: Redigir o pacote essencial v1 | K9: S10 | L9: AGJ | M9: 5 | N9: Seleção do compendium | O9: Backlog
A10: HIIP | B10: Essential package - PHC | C10: Pacote essencial apresentado ao TWG-PHC; posição registada; alterações incorporadas em versão datada | D10: 46402 | E10: Não iniciada | F10: Pacote essencial v1 | G10: Pacote redigido; implicações de recursos estimadas por serviço incluído | H10: 46374 | I10: Não iniciado | J10: Estimar implicações de recursos por serviço incluído | K10: S10 | L10: AGJ | M10: 3 | N10: Pacote v1 | O10: Backlog
A11: HIIP | B11: Essential package - PHC | C11: Pacote essencial apresentado ao TWG-PHC; posição registada; alterações incorporadas em versão datada | D11: 46402 | E11: Não iniciada | F11: Implementação e monitorização | G11: Indicadores de implementação definidos; indicadores de monitorização e avaliação definidos | H11: 46402 | I11: Não iniciado | J11: Definir indicadores de implementação | K11: S11 | L11: AGJ | M11: 2 | N11: Pacote v1 | O11: Backlog
A12: HIIP | B12: Essential package - PHC | C12: Pacote essencial apresentado ao TWG-PHC; posição registada; alterações incorporadas em versão datada | D12: 46402 | E12: Não iniciada | F12: Implementação e monitorização | G12: Indicadores de implementação definidos; indicadores de monitorização e avaliação definidos | H12: 46402 | I12: Não iniciado | J12: Definir indicadores de monitorização e avaliação | K12: S11 | L12: AGJ | M12: 2 | N12: Pacote v1 | O12: Backlog

Sheet 9. Modelo de cuidados
A1: Modelo de cuidados e perfis profissionais - PHC
A3: Projeto | B3: Frente de trabalho (produto) | C3: Validação externa | D3: Data validação | E3: Estado validação | F3: Resultado (output) | G3: Definição de feito (resultado) | H3: Data resultado | I3: Estado resultado | J3: Tarefa | K3: Sprint | L3: Responsável | M3: Estimativa (dias) | N3: Depende de | O3: Estado tarefa | P3: Aprendizado
A4: HIIP | B4: Modelo de cuidados e perfis profissionais - PHC | C4: Modelo apresentado ao TWG-PHC; posição registada; alterações incorporadas em versão datada | D4: 46402 | E4: Não iniciada | F4: Diagnóstico do modelo atual | G4: Modelo vigente descrito; limitações identificadas a partir das entrevistas de campo; composição das equipas e funções efetivamente exercidas mapeadas | H4: 46318 | I4: Não iniciado | J4: Descrever o modelo de cuidados vigente nos CSP | K4: S6 | L4: AGJ | M4: 3 | N4: Síntese qualitativa do campo | O4: Backlog
A5: HIIP | B5: Modelo de cuidados e perfis profissionais - PHC | C5: Modelo apresentado ao TWG-PHC; posição registada; alterações incorporadas em versão datada | D5: 46402 | E5: Não iniciada | F5: Diagnóstico do modelo atual | G5: Modelo vigente descrito; limitações identificadas a partir das entrevistas de campo; composição das equipas e funções efetivamente exercidas mapeadas | H5: 46318 | I5: Não iniciado | J5: Identificar as limitações do modelo atual | K5: S6 | L5: AGJ | M5: 2 | N5: Modelo vigente descrito | O5: Backlog
A6: HIIP | B6: Modelo de cuidados e perfis profissionais - PHC | C6: Modelo apresentado ao TWG-PHC; posição registada; alterações incorporadas em versão datada | D6: 46402 | E6: Não iniciada | F6: Diagnóstico do modelo atual | G6: Modelo vigente descrito; limitações identificadas a partir das entrevistas de campo; composição das equipas e funções efetivamente exercidas mapeadas | H6: 46318 | I6: Não iniciado | J6: Mapear a composição atual das equipas e as funções efetivamente exercidas | K6: S6 | L6: AGJ | M6: 3 | N6: Visitas piloto | O6: Backlog
A7: HIIP | B7: Modelo de cuidados e perfis profissionais - PHC | C7: Modelo apresentado ao TWG-PHC; posição registada; alterações incorporadas em versão datada | D7: 46402 | E7: Não iniciada | F7: Novo modelo de cuidados | G7: Princípios definidos; modelo proposto desenhado; articulação com o essential package explícita | H7: 46346 | I7: Não iniciado | J7: Definir os princípios do novo modelo | K7: S8 | L7: AGJ | M7: 2 | N7: Diagnóstico do modelo atual | O7: Backlog
A8: HIIP | B8: Modelo de cuidados e perfis profissionais - PHC | C8: Modelo apresentado ao TWG-PHC; posição registada; alterações incorporadas em versão datada | D8: 46402 | E8: Não iniciada | F8: Novo modelo de cuidados | G8: Princípios definidos; modelo proposto desenhado; articulação com o essential package explícita | H8: 46346 | I8: Não iniciado | J8: Desenhar o modelo proposto | K8: S8 | L8: AGJ | M8: 5 | N8: Princípios definidos | O8: Backlog
A9: HIIP | B9: Modelo de cuidados e perfis profissionais - PHC | C9: Modelo apresentado ao TWG-PHC; posição registada; alterações incorporadas em versão datada | D9: 46402 | E9: Não iniciada | F9: Novo modelo de cuidados | G9: Princípios definidos; modelo proposto desenhado; articulação com o essential package explícita | H9: 46346 | I9: Não iniciado | J9: Articular o modelo com o essential package | K9: S8 | L9: AGJ | M9: 2 | N9: Critérios do pacote | O9: Backlog
A10: HIIP | B10: Modelo de cuidados e perfis profissionais - PHC | C10: Modelo apresentado ao TWG-PHC; posição registada; alterações incorporadas em versão datada | D10: 46402 | E10: Não iniciada | F10: Perfis profissionais e equipas | G10: Ações por categoria profissional derivadas do UHC Compendium; redesenho das equipas proposto; implicações de formação e de quadro de pessoal identificadas | H10: 46360 | I10: Não iniciado | J10: Derivar do UHC Compendium as ações por categoria profissional | K10: S9 | L10: AGJ | M10: 4 | N10: Seleção do compendium | O10: Backlog
A11: HIIP | B11: Modelo de cuidados e perfis profissionais - PHC | C11: Modelo apresentado ao TWG-PHC; posição registada; alterações incorporadas em versão datada | D11: 46402 | E11: Não iniciada | F11: Perfis profissionais e equipas | G11: Ações por categoria profissional derivadas do UHC Compendium; redesenho das equipas proposto; implicações de formação e de quadro de pessoal identificadas | H11: 46360 | I11: Não iniciado | J11: Definir as ações específicas de cada categoria profissional | K11: S9 | L11: AGJ | M11: 3 | N11: Ações do compendium | O11: Backlog
A12: HIIP | B12: Modelo de cuidados e perfis profissionais - PHC | C12: Modelo apresentado ao TWG-PHC; posição registada; alterações incorporadas em versão datada | D12: 46402 | E12: Não iniciada | F12: Perfis profissionais e equipas | G12: Ações por categoria profissional derivadas do UHC Compendium; redesenho das equipas proposto; implicações de formação e de quadro de pessoal identificadas | H12: 46360 | I12: Não iniciado | J12: Propor o redesenho das equipas | K12: S9 | L12: AGJ | M12: 3 | N12: Ações por categoria | O12: Backlog
A13: HIIP | B13: Modelo de cuidados e perfis profissionais - PHC | C13: Modelo apresentado ao TWG-PHC; posição registada; alterações incorporadas em versão datada | D13: 46402 | E13: Não iniciada | F13: Perfis profissionais e equipas | G13: Ações por categoria profissional derivadas do UHC Compendium; redesenho das equipas proposto; implicações de formação e de quadro de pessoal identificadas | H13: 46360 | I13: Não iniciado | J13: Identificar implicações de formação e de quadro de pessoal | K13: S9 | L13: AGJ | M13: 2 | N13: Redesenho das equipas | O13: Backlog
A14: HIIP | B14: Modelo de cuidados e perfis profissionais - PHC | C14: Modelo apresentado ao TWG-PHC; posição registada; alterações incorporadas em versão datada | D14: 46402 | E14: Não iniciada | F14: Documento do modelo de cuidados | G14: Documento redigido; consulta às ordens e associações profissionais realizada; revisão do country office resolvida | H14: 46374 | I14: Não iniciado | J14: Redigir o documento do modelo de cuidados | K14: S10 | L14: AGJ | M14: 5 | N14: Perfis profissionais | O14: Backlog
A15: HIIP | B15: Modelo de cuidados e perfis profissionais - PHC | C15: Modelo apresentado ao TWG-PHC; posição registada; alterações incorporadas em versão datada | D15: 46402 | E15: Não iniciada | F15: Documento do modelo de cuidados | G15: Documento redigido; consulta às ordens e associações profissionais realizada; revisão do country office resolvida | H15: 46374 | I15: Não iniciado | J15: Consultar as ordens e associações profissionais | K15: S10 | L15: AGJ | M15: 3 | N15: Documento redigido | O15: Backlog
A16: HIIP | B16: Modelo de cuidados e perfis profissionais - PHC | C16: Modelo apresentado ao TWG-PHC; posição registada; alterações incorporadas em versão datada | D16: 46402 | E16: Não iniciada | F16: Documento do modelo de cuidados | G16: Documento redigido; consulta às ordens e associações profissionais realizada; revisão do country office resolvida | H16: 46374 | I16: Não iniciado | J16: Revisão do country office | K16: S10 | L16: AGJ | M16: 2 | N16: Documento redigido | O16: Backlog

Sheet 10. Project scoping
A1: Project scoping - PHC
A3: Projeto | B3: Frente de trabalho (produto) | C3: Validação externa | D3: Data validação | E3: Estado validação | F3: Resultado (output) | G3: Definição de feito (resultado) | H3: Data resultado | I3: Estado resultado | J3: Tarefa | K3: Sprint | L3: Responsável | M3: Estimativa (dias) | N3: Depende de | O3: Estado tarefa | P3: Aprendizado
A4: HIIP | B4: Project scoping - PHC | C4: Project profiles revistos com o MINSA e os financiadores potenciais | D4: 46500 | E4: Não iniciada | F4: Mapeamento de projetos e doadores | G4: Projetos que financiam CSP mapeados; quem financia o quê, para quê e onde identificado; sobreposições e lacunas geográficas e temáticas identificadas | H4: 46318 | I4: Não iniciado | J4: Mapear os projetos que financiam CSP atualmente | K4: S6 | L4: AGJ | M4: 3 | O4: Backlog
A5: HIIP | B5: Project scoping - PHC | C5: Project profiles revistos com o MINSA e os financiadores potenciais | D5: 46500 | E5: Não iniciada | F5: Mapeamento de projetos e doadores | G5: Projetos que financiam CSP mapeados; quem financia o quê, para quê e onde identificado; sobreposições e lacunas geográficas e temáticas identificadas | H5: 46318 | I5: Não iniciado | J5: Identificar quem financia o quê, para quê e onde | K5: S6 | L5: AGJ | M5: 3 | N5: Projetos mapeados | O5: Backlog
A6: HIIP | B6: Project scoping - PHC | C6: Project profiles revistos com o MINSA e os financiadores potenciais | D6: 46500 | E6: Não iniciada | F6: Mapeamento de projetos e doadores | G6: Projetos que financiam CSP mapeados; quem financia o quê, para quê e onde identificado; sobreposições e lacunas geográficas e temáticas identificadas | H6: 46318 | I6: Não iniciado | J6: Identificar sobreposições e lacunas geográficas e temáticas | K6: S6 | L6: AGJ | M6: 2 | N6: Mapeamento | O6: Backlog
A7: HIIP | B7: Project scoping - PHC | C7: Project profiles revistos com o MINSA e os financiadores potenciais | D7: 46500 | E7: Não iniciada | F7: Project profiles | G7: Áreas selecionadas com o MINSA; perfis desenvolvidos; perfis revistos com MINSA e financiadores | H7: 46500 | I7: Não iniciado | J7: Selecionar 2 a 3 áreas para desenvolvimento de perfis | K7: S16 | L7: AGJ | M7: 2 | N7: Pacotes de investimento | O7: Backlog
A8: HIIP | B8: Project scoping - PHC | C8: Project profiles revistos com o MINSA e os financiadores potenciais | D8: 46500 | E8: Não iniciada | F8: Project profiles | G8: Áreas selecionadas com o MINSA; perfis desenvolvidos; perfis revistos com MINSA e financiadores | H8: 46500 | I8: Não iniciado | J8: Desenvolver os project profiles | K8: S17 | L8: AGJ | M8: 10 | N8: Áreas selecionadas | O8: Backlog
A9: HIIP | B9: Project scoping - PHC | C9: Project profiles revistos com o MINSA e os financiadores potenciais | D9: 46500 | E9: Não iniciada | F9: Project profiles | G9: Áreas selecionadas com o MINSA; perfis desenvolvidos; perfis revistos com MINSA e financiadores | H9: 46500 | I9: Não iniciado | J9: Rever os perfis com o MINSA e os financiadores potenciais | K9: S18 | L9: AGJ | M9: 4 | N9: Perfis desenvolvidos | O9: Backlog

Sheet 11. Financiamento
A1: Mobilização de financiamento - PHC
A3: Projeto | B3: Frente de trabalho (produto) | C3: Validação externa | D3: Data validação | E3: Estado validação | F3: Resultado (output) | G3: Definição de feito (resultado) | H3: Data resultado | I3: Estado resultado | J3: Tarefa | K3: Sprint | L3: Responsável | M3: Estimativa (dias) | N3: Depende de | O3: Estado tarefa | P3: Aprendizado
A4: HIIP | B4: Mobilização de financiamento - PHC | C4: Compromissos de financiadores registados; proposta de empréstimo assinada | D4: 46556 | E4: Não iniciada | F4: Engajamento de financiadores | G4: BEI engajado nas discussões e na priorização; outros doadores e delegação da UE mapeados; reuniões de validação e buy-in realizadas com registo | H4: 46514 | I4: Não iniciado | J4: Engajar o BEI nas discussões sobre áreas de investimento | K4: S17 | L4: AGJ | M4: 3 | N4: Investment plan v1 | O4: Backlog
A5: HIIP | B5: Mobilização de financiamento - PHC | C5: Compromissos de financiadores registados; proposta de empréstimo assinada | D5: 46556 | E5: Não iniciada | F5: Engajamento de financiadores | G5: BEI engajado nas discussões e na priorização; outros doadores e delegação da UE mapeados; reuniões de validação e buy-in realizadas com registo | H5: 46514 | I5: Não iniciado | J5: Envolver o BEI nos exercícios de priorização | K5: S18 | L5: AGJ | M5: 3 | N5: BEI engajado | O5: Backlog
A6: HIIP | B6: Mobilização de financiamento - PHC | C6: Compromissos de financiadores registados; proposta de empréstimo assinada | D6: 46556 | E6: Não iniciada | F6: Engajamento de financiadores | G6: BEI engajado nas discussões e na priorização; outros doadores e delegação da UE mapeados; reuniões de validação e buy-in realizadas com registo | H6: 46514 | I6: Não iniciado | J6: Mapear outros doadores e a delegação da UE | K6: S18 | L6: AGJ | M6: 3 | O6: Backlog
A7: HIIP | B7: Mobilização de financiamento - PHC | C7: Compromissos de financiadores registados; proposta de empréstimo assinada | D7: 46556 | E7: Não iniciada | F7: Engajamento de financiadores | G7: BEI engajado nas discussões e na priorização; outros doadores e delegação da UE mapeados; reuniões de validação e buy-in realizadas com registo | H7: 46514 | I7: Não iniciado | J7: Organizar as reuniões de validação e buy-in | K7: S19 | L7: AGJ | M7: 5 | N7: Doadores mapeados | O7: Backlog
A8: HIIP | B8: Mobilização de financiamento - PHC | C8: Compromissos de financiadores registados; proposta de empréstimo assinada | D8: 46556 | E8: Não iniciada | F8: Empréstimo do Banco Mundial | G8: Pacote documental preparado; versão única e datada nas duas vias; questões técnicas respondidas; proposta final consolidada | H8: 46556 | I8: Não iniciado | J8: Preparar o pacote documental para o Banco Mundial | K8: S19 | L8: AGJ | M8: 3 | N8: Investment case; investment plan | O8: Backlog
A9: HIIP | B9: Mobilização de financiamento - PHC | C9: Compromissos de financiadores registados; proposta de empréstimo assinada | D9: 46556 | E9: Não iniciada | F9: Empréstimo do Banco Mundial | G9: Pacote documental preparado; versão única e datada nas duas vias; questões técnicas respondidas; proposta final consolidada | H9: 46556 | I9: Não iniciado | J9: Garantir que a versão que segue pela Ministra e pela OMS é a mesma, datada | K9: S19 | L9: AGJ | M9: 1 | N9: Pacote documental | O9: Backlog
A10: HIIP | B10: Mobilização de financiamento - PHC | C10: Compromissos de financiadores registados; proposta de empréstimo assinada | D10: 46556 | E10: Não iniciada | F10: Empréstimo do Banco Mundial | G10: Pacote documental preparado; versão única e datada nas duas vias; questões técnicas respondidas; proposta final consolidada | H10: 46556 | I10: Não iniciado | J10: Acompanhar a negociação e responder às questões técnicas | K10: S20 | L10: AGJ | M10: 4 | N10: Pacote entregue | O10: Backlog
A11: HIIP | B11: Mobilização de financiamento - PHC | C11: Compromissos de financiadores registados; proposta de empréstimo assinada | D11: 46556 | E11: Não iniciada | F11: Empréstimo do Banco Mundial | G11: Pacote documental preparado; versão única e datada nas duas vias; questões técnicas respondidas; proposta final consolidada | H11: 46556 | I11: Não iniciado | J11: Consolidar a proposta final | K11: S21 | L11: AGJ | M11: 5 | N11: Negociação | O11: Backlog

Sheet 12. Relatórios
A1: Relatórios contratuais do HIIP
A3: Projeto | B3: Frente de trabalho (produto) | C3: Validação externa | D3: Data validação | E3: Estado validação | F3: Resultado (output) | G3: Definição de feito (resultado) | H3: Data resultado | I3: Estado resultado | J3: Tarefa | K3: Sprint | L3: Responsável | M3: Estimativa (dias) | N3: Depende de | O3: Estado tarefa | P3: Aprendizado
A4: HIIP | B4: Relatórios contratuais do HIIP | F4: Calendário de reporte | G4: Calendário contratual confirmado e inscrito no plano | H4: 46276 | I4: Não iniciado | J4: Confirmar o calendário contratual de reporte | K4: S3 | L4: AGJ | M4: 1 | O4: Backlog
A5: HIIP | B5: Relatórios contratuais do HIIP | F5: Relatórios de progresso | G5: Relatórios submetidos e aceites nos prazos contratuais | I5: Não iniciado | J5: Relatório de progresso - período 1 | K5: TBC | L5: AGJ | M5: 3 | N5: Calendário de reporte | O5: Backlog
A6: HIIP | B6: Relatórios contratuais do HIIP | F6: Relatórios de progresso | G6: Relatórios submetidos e aceites nos prazos contratuais | I6: Não iniciado | J6: Relatório de progresso - período 2 | K6: TBC | L6: AGJ | M6: 3 | N6: Calendário de reporte | O6: Backlog
A7: HIIP | B7: Relatórios contratuais do HIIP | F7: Relatórios de progresso | G7: Relatórios submetidos e aceites nos prazos contratuais | I7: Não iniciado | J7: Relatório intercalar | K7: TBC | L7: AGJ | M7: 5 | N7: Calendário de reporte | O7: Backlog
A8: HIIP | B8: Relatórios contratuais do HIIP | F8: Relatórios de progresso | G8: Relatórios submetidos e aceites nos prazos contratuais | I8: Não iniciado | J8: Relatório anual ou final | K8: TBC | L8: AGJ | M8: 5 | N8: Calendário de reporte | O8: Backlog
